{
  "version": 1.0,
  "song": [
    {
      "id": "1",
      "Timestamp": 45869.609947523146,
      "Title": "ለባርኮትነ ንኡ",
      "singer": "ሌላ",
      "about": [
        "የቅዱሳን ጻድቃንና ሰማዕታት"
      ],
      "minor_holidays": [],
      "main_holidays": [],
      "angels": [],
      "Trinity_Song": {
        "Tir": false,
        "Hamle": false,
        "Mesgana": false
      },
      "St_Mary_Song": {
        "Yekatit": false,
        "Nehase": false,
        "Mesgana": false
      },
      "K_Gebriel_Song": {
        "Tahsas": false,
        "Hamle": false,
        "Mesgana": false
      },
      "songLyrics": {
        "isShortSong": true,
        "shortLyrics": {
          "lyrics": "ሰላም ለክሙ እንጦንስ ወመቃርስ አቢብ ሲኖዳ ገብለ መንፈስ ቅዱስ /2/\nለባርኮትነ ንኡ ውስተ ጽርሐ ዛቲ መቅደስ ተክለ ሃይማኖት አኖሬዎስ ኤዎስታጤዎስ ሳሙኤል ተክለ አልፋ በብኑዳ ኪሮስ /2/",
          "translation": "እንጦንስ መቃርስ አቢብ ሲኖዳ ገብለ መንፈስ ቅዱስ\nሰላምታ ይገባችኋል ተክለ ሃይማኖት \nአኖሬዎስ ኤዎስታጤዎስ ሳሙኤል ተክለ አልፋ በብኑዳ ኪሮስ \nትባርኩን ዘንድ በዚህች መቅደስ ኑ"
        },
        "longLyrics": {
          "chorus": "",
          "verse": [
            "",
            "",
            "",
            "",
            "",
            "",
            "",
            "",
            "",
            ""
          ]
        }
      }
    },
    {
      "id": "2",
      "Timestamp": 45868.66326037037,
      "Title": "ለተክለ ሃይማኖት ጻድቅ ",
      "singer": "ሌላ",
      "about": [
        "የቅዱሳን ጻድቃንና ሰማዕታት"
      ],
      "minor_holidays": [],
      "main_holidays": [],
      "angels": [],
      "Trinity_Song": {
        "Tir": false,
        "Hamle": false,
        "Mesgana": false
      },
      "St_Mary_Song": {
        "Yekatit": false,
        "Nehase": false,
        "Mesgana": false
      },
      "K_Gebriel_Song": {
        "Tahsas": false,
        "Hamle": false,
        "Mesgana": false
      },
      "songLyrics": {
        "isShortSong": false,
        "shortLyrics": {
          "lyrics": "",
          "translation": ""
        },
        "longLyrics": {
          "chorus": "ለተክለ ሃይማኖት ጻድቅ መጠነ በዝሃ ህማሙ\nትዌድሶ ደብረ ሊባኖሰ ገዳሙ /2/ ",
          "verse": [
            "እምነ አድባራት ኩሎን ዘተለአለት በስሙ \nትዌድሶ ደብረ ሊባኖሰ ገዳሙ /2/ ",
            "እስመ በውስቴታ ተገብረ ፍልሠተ ሥጋሁ ወአጽሙ \nትዌድሶ ደብረ ሊባኖሰ ገዳሙ /2/ ",
            "ኢየሱስ ክርስቶሰ እንተ ቀደሳ በደሙ \n ትዌድሶ ደብረ ሊባኖሰ ገዳሙ /2/ ",
            "ትርጉም፦ ጻድቁ ተክለሃይማኖት ብዙ ህማም የተቀበለባት ቅዱስ አጽሙ ያረፈባት በስሙ ከታነጹት አድባራት ሁሉ ከፍ ያለች ኢየሱስ ክርስቶስ በደሙ የቀደሳት ደብረ ሊባኖስ ታመሰግነዋለች\n",
            "",
            "",
            "",
            "",
            "",
            ""
          ]
        }
      }
    },
    {
      "id": "3",
      "Timestamp": 45866.60862568287,
      "Title": "ሐዋርያው መነኩሴ",
      "singer": "ሌላ",
      "singerOther": "ቀሲስ አሸናፊ ገ/ማርያም",
      "about": [
        "የቅዱሳን ጻድቃንና ሰማዕታት"
      ],
      "minor_holidays": [],
      "main_holidays": [],
      "angels": [],
      "Trinity_Song": {
        "Tir": false,
        "Hamle": false,
        "Mesgana": false
      },
      "St_Mary_Song": {
        "Yekatit": false,
        "Nehase": false,
        "Mesgana": false
      },
      "K_Gebriel_Song": {
        "Tahsas": false,
        "Hamle": false,
        "Mesgana": false
      },
      "songLyrics": {
        "isShortSong": false,
        "shortLyrics": {
          "lyrics": "",
          "translation": ""
        },
        "longLyrics": {
          "chorus": "ሐዋርያው መነኩሴ የመረጡህ ሥላሴ /2/ \nዋስ ጠበቃ ሁናት ተክለአብ ለነፍሴ /2/ ",
          "verse": [
            "ዳሞት ትናገረው ያንተን ሐዋርያነት \nየወንጌል ገበሬ የጣኦታት ጠላት \nጸሎተኛው ቅዱስ አባ ተክለሐይማኖት \nክንፍን የተሸለምክ እንደ ሰማይ መላእክት /2/ ",
            "ብራናው ሲገለጥ ገድለ ተክለ ሃይማኖት \nከሰው ልጅ ልቡና ይወጣል አጋንንት \nየቅዳሴው እጣን ሲወጣ ከዋሻው \nምድርን ይባርካል ጸሎቱ ምህላው/2/ ",
            "ከሱራፌል ተርታ ቆመህ በማጠንህ \nቅዱስ ሥሉስ  እያልህ ስታመሰግን\n ጸሎት ትሩፋትህ ትሕትና ስግደትህ \nጾምህ ከፍ አድርጎ ሰማይ አደረሰህ/2/ ",
            "ዛፉ ሲመነገል አምላክ የተባለው \nመቶሎሚ ሲያፍር ትልቅ ሰው ነኝ ያለው \nየጻድቁ ጸሎት ብዙ ነው ምሥጢሩ \nስድስት ክንፉ አወጣ ቢቆረጥ አንድ እግሩ /2/ ",
            "የኢትዮጵያን ምድር አረስከው በመስቀል \nጭንጫው ፈራረሰ ተዘራበት ወንጌል \nትናንት የዘራኸው ዛሬም ለእኛ ሆንዋል\nአምላከ ተክለ አብ ብለን ተምረናል",
            "",
            "",
            "",
            "",
            ""
          ]
        }
      }
    },
    {
      "id": "4",
      "Timestamp": 45869.42676164352,
      "Title": "መሠረተ ዜማ ",
      "singer": "ሌላ",
      "about": [
        "የቅዱሳን ጻድቃንና ሰማዕታት"
      ],
      "minor_holidays": [],
      "main_holidays": [],
      "angels": [],
      "Trinity_Song": {
        "Tir": false,
        "Hamle": false,
        "Mesgana": false
      },
      "St_Mary_Song": {
        "Yekatit": false,
        "Nehase": false,
        "Mesgana": false
      },
      "K_Gebriel_Song": {
        "Tahsas": false,
        "Hamle": false,
        "Mesgana": false
      },
      "songLyrics": {
        "isShortSong": true,
        "shortLyrics": {
          "lyrics": "መሠረተ ዜማ /ወጠነ /2/ ያሬድ ካህን /2/\nያሬድ /3/ ያሬድ ካህን /2/ ጥዑመ ልሳን /2/",
          "translation": "የዜማን መሠረት /ጀመረ/2/ ያሬድ ካህን /2/\nያሬድ /3/ ያሬድ ካህን /2/ ጥዑመ ልሳን /2/"
        },
        "longLyrics": {
          "chorus": "",
          "verse": [
            "",
            "",
            "",
            "",
            "",
            "",
            "",
            "",
            "",
            ""
          ]
        }
      }
    },
    {
      "id": "5",
      "Timestamp": 45869.60252159722,
      "Title": "መጠወ ነፍሶ",
      "singer": "ሌላ",
      "about": [
        "የቅዱሳን ጻድቃንና ሰማዕታት"
      ],
      "minor_holidays": [],
      "main_holidays": [],
      "angels": [],
      "Trinity_Song": {
        "Tir": false,
        "Hamle": false,
        "Mesgana": false
      },
      "St_Mary_Song": {
        "Yekatit": false,
        "Nehase": false,
        "Mesgana": false
      },
      "K_Gebriel_Song": {
        "Tahsas": false,
        "Hamle": false,
        "Mesgana": false
      },
      "songLyrics": {
        "isShortSong": true,
        "shortLyrics": {
          "lyrics": "መጠወ ነፍሶ ወመተርዎ ክሳዶ /2/\nኧኸ ተፈጸመ /3/ አክሊለ ስሙ ለቅዱስ መርቆሬዎስ /2/",
          "translation": "ነፍሱን ሰጠ ራሱንም ቆረጡት የቅዱስ መርቆሬዎስ የክብርአክሊል ተፈጸመ"
        },
        "longLyrics": {
          "chorus": "",
          "verse": [
            "",
            "",
            "",
            "",
            "",
            "",
            "",
            "",
            "",
            ""
          ]
        }
      }
    },
    {
      "id": "6",
      "Timestamp": 45869.603831354165,
      "Title": "ሰላም ለከ ",
      "singer": "ሌላ",
      "about": [
        "የቅዱሳን ጻድቃንና ሰማዕታት"
      ],
      "minor_holidays": [],
      "main_holidays": [],
      "angels": [],
      "Trinity_Song": {
        "Tir": false,
        "Hamle": false,
        "Mesgana": false
      },
      "St_Mary_Song": {
        "Yekatit": false,
        "Nehase": false,
        "Mesgana": false
      },
      "K_Gebriel_Song": {
        "Tahsas": false,
        "Hamle": false,
        "Mesgana": false
      },
      "songLyrics": {
        "isShortSong": true,
        "shortLyrics": {
          "lyrics": "ሰላም ለከ ኦ መርቆሬዎስ ዘሮሜ /2/\nሰማዕት ተጋድሎ /3/ ኮንከ ፈፃሜ /2/\n",
          "translation": "የሮሜው ቅዱስ መርቆሬዎስ ሆይ ሰላም እልሃለሁ የሰማዕትነት ተጋድሎ ፈፃሚ ሆንክ"
        },
        "longLyrics": {
          "chorus": "",
          "verse": [
            "",
            "",
            "",
            "",
            "",
            "",
            "",
            "",
            "",
            ""
          ]
        }
      }
    },
    {
      "id": "7",
      "Timestamp": 45869.42507564815,
      "Title": "ሰባኬ ወንጌል ",
      "singer": "ሌላ",
      "about": [
        "የቅዱሳን ጻድቃንና ሰማዕታት"
      ],
      "minor_holidays": [],
      "main_holidays": [],
      "angels": [],
      "Trinity_Song": {
        "Tir": false,
        "Hamle": false,
        "Mesgana": false
      },
      "St_Mary_Song": {
        "Yekatit": false,
        "Nehase": false,
        "Mesgana": false
      },
      "K_Gebriel_Song": {
        "Tahsas": false,
        "Hamle": false,
        "Mesgana": false
      },
      "songLyrics": {
        "isShortSong": true,
        "shortLyrics": {
          "lyrics": "ሰባኬ ወንጌል መጋቤ ሃይማኖት ለቤተ ክርስቲያን \nዘይደምፅ ቀርን ነባቢ ለቤተክርስቲያን /2/\nያሬድ ፀሐይ ዘኢትዮጵያ ዓምደ ብርሃን ዘቤተ ክርስቲያን\nመልአክ ዘበምድር ዘበምድር መልአክ /2/",
          "translation": ""
        },
        "longLyrics": {
          "chorus": "",
          "verse": [
            "",
            "",
            "",
            "",
            "",
            "",
            "",
            "",
            "",
            ""
          ]
        }
      }
    },
    {
      "id": "8",
      "Timestamp": 45869.60735989583,
      "Title": "ሰአለ ሥርየተ ኃጢአት ",
      "singer": "ሌላ",
      "about": [
        "የቅዱሳን ጻድቃንና ሰማዕታት"
      ],
      "minor_holidays": [],
      "main_holidays": [],
      "angels": [],
      "Trinity_Song": {
        "Tir": false,
        "Hamle": false,
        "Mesgana": false
      },
      "St_Mary_Song": {
        "Yekatit": false,
        "Nehase": false,
        "Mesgana": false
      },
      "K_Gebriel_Song": {
        "Tahsas": false,
        "Hamle": false,
        "Mesgana": false
      },
      "songLyrics": {
        "isShortSong": true,
        "shortLyrics": {
          "lyrics": "ሰአለ ሥርየተ ኃጢአት ለእለ ወገርዎ /2/\nወይቤ ስረይ ሎሙ ዘንተ ኃጢአቶሙ /2/",
          "translation": "ቅዱስ እስጢፋኖስ ለወገኖቹ የኃጢአት ሥርየት ለመነ ኃጢአታቸውንም ይቅር በላቸው አለ"
        },
        "longLyrics": {
          "chorus": "",
          "verse": [
            "",
            "",
            "",
            "",
            "",
            "",
            "",
            "",
            "",
            ""
          ]
        }
      }
    },
    {
      "id": "9",
      "Timestamp": 45862.516322118056,
      "Title": "ሰአሉ ለነ",
      "singer": "ሌላ",
      "singerOther": "አዳነች አስፋው",
      "about": [
        "የቅዱሳን ጻድቃንና ሰማዕታት"
      ],
      "minor_holidays": [],
      "main_holidays": [],
      "angels": [],
      "Trinity_Song": {
        "Tir": false,
        "Hamle": false,
        "Mesgana": false
      },
      "St_Mary_Song": {
        "Yekatit": false,
        "Nehase": false,
        "Mesgana": false
      },
      "K_Gebriel_Song": {
        "Tahsas": false,
        "Hamle": false,
        "Mesgana": false
      },
      "songLyrics": {
        "isShortSong": false,
        "shortLyrics": {
          "lyrics": "",
          "translation": ""
        },
        "longLyrics": {
          "chorus": "ሰአሉ ለነ ቅዱሳን መላእክት\nሰአሉ ለነ ጻድቃን ሰማዕታት\nኅበ አምላከ ምሕረት ሰአሉ ለነ\nለምኑልን ቅዱሳን መላእክት /2/",
          "verse": [
            "ለምኑልን ጻድቃን ሰማዕታት\nወደ አምላከ ምሕረት ለምኑልን\nአንተ የመረጥከውን ማን ይከሳል\nያፀደከውን ማን ይወቅሳል\nለሚገባው ክብርን መስጠት\nታዝዟል እና በመጻሕፍት\nያከበርካቸውን ባሪያዎችህን\nእናከብራለን ቅዱሳንህን/ 2/",
            "ሁሉ መዳን እንዲይዙ\nየሚላኩ የሚታዘዙ\nሠርክ በፊትህ እየቆሙ\nጥዑም ቅዳሴን እያሰሙ\nበምስጋናቸው የሚያከብሩህን\nእናከብራለን መላእክትህን / 2/",
            "ጤዛ ልሰው ዳዋ ጥሰው\nዋዕይ ቁሩንም ታግሠው\nበየፍርክታው በየዱሩ\nሌጦ ለብሰው እየዞሩ\nበፅናታቸው ያከበሩህን\nእናከብራለን ጻድቃንህን /2/",
            "እንደሚታረዱ በጎች ሆነው\nአንገታቸውን ለሰይፍ ሰጥተው\nስለ ስምህ እየተጣሉ\nከአንበሳ ጋር እየታገሉ\nበተጋድሏቸው ያከበሩህን\nእናከብራለን ሰማዕታትን /2/",
            "ከሕያው ቃልህ እየጠቀሱ\nመናፍቃንን ድል የነሱ\nበገዛ ደምህ የዋጀሀትን\nቤተ ክርስትያንን የጠበቋትን\nበሕይወታቸው ያስደሰቱህን\nእናከብራለን ቅዱሳንህን/2/",
            "",
            "",
            "",
            "",
            ""
          ]
        }
      }
    },
    {
      "id": "10",
      "Timestamp": 45863.941714699075,
      "Title": "ቅዱሳን ዘእምኀቤከ",
      "singer": "ሌላ",
      "about": [
        "የቅዱሳን ጻድቃንና ሰማዕታት"
      ],
      "minor_holidays": [],
      "main_holidays": [
        "ጰራቅሊጦስ"
      ],
      "angels": [],
      "Trinity_Song": {
        "Tir": false,
        "Hamle": false,
        "Mesgana": false
      },
      "St_Mary_Song": {
        "Yekatit": false,
        "Nehase": false,
        "Mesgana": false
      },
      "K_Gebriel_Song": {
        "Tahsas": false,
        "Hamle": false,
        "Mesgana": false
      },
      "songLyrics": {
        "isShortSong": true,
        "shortLyrics": {
          "lyrics": "ቅዱሳን ዘእምኀቤከ ወንጹሐነ ይኲኑ /2/\nጰራቅሊጦስሃ /2/ ዲቤነ መንፈስከ ፈኑ /2/",
          "translation": "እንደአንተ ቅዱሳንና ንጹሐን ይሁኑ\nጰራቅሊጦስ መንፈስህን በእኛላይ ላክ"
        },
        "longLyrics": {
          "chorus": "",
          "verse": [
            "",
            "",
            "",
            "",
            "",
            "",
            "",
            "",
            "",
            ""
          ]
        }
      }
    },
    {
      "id": "11",
      "Timestamp": 45869.600547361115,
      "Title": "ቅዱስ መርቆሬዎስ",
      "singer": "ሌላ",
      "about": [
        "የቅዱሳን ጻድቃንና ሰማዕታት"
      ],
      "minor_holidays": [],
      "main_holidays": [],
      "angels": [],
      "Trinity_Song": {
        "Tir": false,
        "Hamle": false,
        "Mesgana": false
      },
      "St_Mary_Song": {
        "Yekatit": false,
        "Nehase": false,
        "Mesgana": false
      },
      "K_Gebriel_Song": {
        "Tahsas": false,
        "Hamle": false,
        "Mesgana": false
      },
      "songLyrics": {
        "isShortSong": true,
        "shortLyrics": {
          "lyrics": "ቅዱስ መርቆሬዎስ ሰማዕታዊው የኛ አባት /2/\nተዋሕዶን ምሰሶ ሆንካት /2/",
          "translation": "ከእናትህ ማህጸን ቸር አምላክ ሲያስብህ /2/\nለኢትዮጲያ ብርሃን አረገህ /2/"
        },
        "longLyrics": {
          "chorus": "",
          "verse": [
            "",
            "",
            "",
            "",
            "",
            "",
            "",
            "",
            "",
            ""
          ]
        }
      }
    },
    {
      "id": "12",
      "Timestamp": 45869.60909694445,
      "Title": "በብዙ አህጉር ",
      "singer": "ሌላ",
      "about": [
        "የቅዱሳን ጻድቃንና ሰማዕታት"
      ],
      "minor_holidays": [],
      "main_holidays": [],
      "angels": [],
      "Trinity_Song": {
        "Tir": false,
        "Hamle": false,
        "Mesgana": false
      },
      "St_Mary_Song": {
        "Yekatit": false,
        "Nehase": false,
        "Mesgana": false
      },
      "K_Gebriel_Song": {
        "Tahsas": false,
        "Hamle": false,
        "Mesgana": false
      },
      "songLyrics": {
        "isShortSong": true,
        "shortLyrics": {
          "lyrics": "በብዙ አህጉር የዞርክ የጌታን ወንጌል ያስተማርክ /2/\nየዲቁናን ግብር የፈፀምክ /ብፁዕ ነህ/2/ እስጢፋኖስ ብፁዕ ነህ /2/",
          "translation": ""
        },
        "longLyrics": {
          "chorus": "",
          "verse": [
            "",
            "",
            "",
            "",
            "",
            "",
            "",
            "",
            "",
            ""
          ]
        }
      }
    },
    {
      "id": "13",
      "Timestamp": 45861.70898761574,
      "Title": "በእውነት ሰማዕታት",
      "singer": "ማሕበረ ቅዱሳን",
      "about": [
        "የቅዱሳን ጻድቃንና ሰማዕታት"
      ],
      "minor_holidays": [],
      "main_holidays": [],
      "angels": [],
      "Trinity_Song": {
        "Tir": false,
        "Hamle": false,
        "Mesgana": false
      },
      "St_Mary_Song": {
        "Yekatit": false,
        "Nehase": false,
        "Mesgana": false
      },
      "K_Gebriel_Song": {
        "Tahsas": false,
        "Hamle": false,
        "Mesgana": false
      },
      "songLyrics": {
        "isShortSong": false,
        "shortLyrics": {
          "lyrics": "",
          "translation": ""
        },
        "longLyrics": {
          "chorus": "በእውነት ሰማዕታት ምርጦችህ ሆኑ\nየዓለምን መንግሥት ክብሩን ሁሉ ስለመነኑ",
          "verse": [
            "ተመተሩ ተቆራረጡ\nስለ ስምህ ብለው ያላቸውን ሁሉ እያጡ\nተቃጠሉ በሰይፍ አለቁ\nየሚመጣውን ክብር መንግሥትን ስለናፈቁ",
            "ምድራዊውን መንግሥት ትተው\nወደ ማያልፈው ክብር ተጓዙ ከዓለም ወጥተው\nወደ ተኩላዎች መንጋ ተላኩ\nቃለ ወንጌልህን በአሕዛብ መንደር ሊሰብኩ",
            "ወደ ሸንጎ አሳለፏቸው\nበነገሥታቱ ፊት በአደባባይ ሊያስጨንቋቸው\nበዚያች ሰዓት ሳይሳቀቁ\nለሚናገሩት ቃል ሳያስቡ ሳይጨነቁ",
            "ጰራቅሊጦስ አጽናኝ ነውና\nእስከ መጨረሻው ለታገሠው በእምነት ለጸና\nመከራውን እያስቻላቸው\nእግዚአብሔር የድልን ዘውድ አቀዳጃቸው",
            "",
            "",
            "",
            "",
            "",
            ""
          ]
        }
      }
    },
    {
      "id": "14",
      "Timestamp": 45869.60633284722,
      "Title": "በከየት ገዳምከ ",
      "singer": "ሌላ",
      "about": [
        "የቅዱሳን ጻድቃንና ሰማዕታት"
      ],
      "minor_holidays": [],
      "main_holidays": [],
      "angels": [],
      "Trinity_Song": {
        "Tir": false,
        "Hamle": false,
        "Mesgana": false
      },
      "St_Mary_Song": {
        "Yekatit": false,
        "Nehase": false,
        "Mesgana": false
      },
      "K_Gebriel_Song": {
        "Tahsas": false,
        "Hamle": false,
        "Mesgana": false
      },
      "songLyrics": {
        "isShortSong": true,
        "shortLyrics": {
          "lyrics": "ሃሌ ሉያ ሃሌ ሃሌ ሉያ በከየት ገዳምከ /2/\nዋልድባ ቅድስት ዜና ሞትከ ሰሚዓ ምድረ ዋልድባ ቅድስት /2/",
          "translation": "ዋልድባ ገዳምህ የሞትህን ዜና ስትሰማ አዘነች።"
        },
        "longLyrics": {
          "chorus": "",
          "verse": [
            "",
            "",
            "",
            "",
            "",
            "",
            "",
            "",
            "",
            ""
          ]
        }
      }
    },
    {
      "id": "15",
      "Timestamp": 45869.44359678241,
      "Title": "በጾም ወበጸሎት",
      "singer": "ሌላ",
      "singerOther": "ሰንበት ት/ቤት ማደራጃ",
      "about": [
        "የቅዱሳን ጻድቃንና ሰማዕታት"
      ],
      "minor_holidays": [],
      "main_holidays": [],
      "angels": [],
      "Trinity_Song": {
        "Tir": false,
        "Hamle": false,
        "Mesgana": false
      },
      "St_Mary_Song": {
        "Yekatit": false,
        "Nehase": false,
        "Mesgana": false
      },
      "K_Gebriel_Song": {
        "Tahsas": false,
        "Hamle": false,
        "Mesgana": false
      },
      "songLyrics": {
        "isShortSong": true,
        "shortLyrics": {
          "lyrics": "ሃሌ ሃሌሉያ በጾም ወበጸሎት /2/\nተመጠወ ሙሴ ኦሪተ አሥሮነ ቃላተ\nተመጠወ ሙሴ ጽላተ አሥሮነ ቃላተ",
          "translation": "ሃሌ ሃሌሉያ በጾምና በጸሎት /2/\nተቀበለ ሙሴ ኦሪትን አሠርቱን ቃላትን\nተቀበለ ሙሴ ጽላትን አሠርቱን ቃላትን\n"
        },
        "longLyrics": {
          "chorus": "",
          "verse": [
            "",
            "",
            "",
            "",
            "",
            "",
            "",
            "",
            "",
            ""
          ]
        }
      }
    },
    {
      "id": "16",
      "Timestamp": 45868.67196603009,
      "Title": "በፍቅረ አምላኩ ",
      "singer": "ሌላ",
      "about": [
        "የቅዱሳን ጻድቃንና ሰማዕታት"
      ],
      "minor_holidays": [],
      "main_holidays": [],
      "angels": [],
      "Trinity_Song": {
        "Tir": false,
        "Hamle": false,
        "Mesgana": false
      },
      "St_Mary_Song": {
        "Yekatit": false,
        "Nehase": false,
        "Mesgana": false
      },
      "K_Gebriel_Song": {
        "Tahsas": false,
        "Hamle": false,
        "Mesgana": false
      },
      "songLyrics": {
        "isShortSong": true,
        "shortLyrics": {
          "lyrics": "በፍቅረ አምላኩ ጊዮርጊስ /2/\nተጋደለ /4/ ወፈጸመ ገድሎ /2/",
          "translation": "በአምላኩ ፍቅር ቅዱስ ጊዮርጊስ ተጋድሎውን ፈጸመ"
        },
        "longLyrics": {
          "chorus": "",
          "verse": [
            "",
            "",
            "",
            "",
            "",
            "",
            "",
            "",
            "",
            ""
          ]
        }
      }
    },
    {
      "id": "17",
      "Timestamp": 45867.482518495366,
      "Title": "በፍኖተ ጽድቁ",
      "singer": "ሌላ",
      "singerOther": "መዝሙር ዘማሪ ወንደሰን ",
      "about": [
        "የቅዱሳን ጻድቃንና ሰማዕታት"
      ],
      "minor_holidays": [],
      "main_holidays": [],
      "angels": [],
      "Trinity_Song": {
        "Tir": false,
        "Hamle": false,
        "Mesgana": false
      },
      "St_Mary_Song": {
        "Yekatit": false,
        "Nehase": false,
        "Mesgana": false
      },
      "K_Gebriel_Song": {
        "Tahsas": false,
        "Hamle": false,
        "Mesgana": false
      },
      "songLyrics": {
        "isShortSong": false,
        "shortLyrics": {
          "lyrics": "",
          "translation": ""
        },
        "longLyrics": {
          "chorus": "በፍኖተ ጽድቁ ኢትዮጵያን ያበራ\nድንቅ ተዓምራትን በሁሉም የሠራ\nመንበሩን ለማጠን በይባቤ ዐረገ\nተክለሃይማኖት ነው ጽድቅን ያደረገ",
          "verse": [
            "ጻድቅ ጸሎተኛ የእግዚእ ኃረያ ፍሬ\nአምላክ የመረጠው የወንጌል ገበሬ\nሞቶሎሚ ቢያብል በክፋት ጥማሬ\nለክብር አበቃኸው አጠመከው ዛሬ",
            "ሰባት ዓመት ቆሞ ለጸሎት የተጋ\nከፈጣሪ አምላክ የተሰጠው ጸጋ\nበአንድ እግሩ የቆመ ሲጠባ ሲነጋ\nአማልዶ እንዲያድነን እርሱን እንጠጋ",
            "ደግ ሰው መምህር የተዋሕዶ አርበኛ\nወንጌላዊ ካህን የጽድቅ መገኛ\nኃጢአታችን በዝታ እንዳንዝል ዳግመኛ\nበምልጃህ አስበን ተመልከት ወደኛ",
            "በእሥራ አርባዕቱ ካህናተ ሰማይ \nመንበሩን ያጠንከው ከፈጣሪ አዶናይ\nጸልይ ለኢትዮጲያ ከበደል ከኃጢአት\nጸድቅ እንጂ ኩነኔ ፍጹም እንዳያያት",
            "",
            "",
            "",
            "",
            "",
            ""
          ]
        }
      }
    },
    {
      "id": "18",
      "Timestamp": 45866.605223506944,
      "Title": "ተክለ ሃይማኖት ባህታዊ",
      "singer": "ሌላ",
      "singerOther": "ዘማሪት ፀዳለ ጎበዜ",
      "about": [
        "የቅዱሳን ጻድቃንና ሰማዕታት"
      ],
      "minor_holidays": [],
      "main_holidays": [],
      "angels": [],
      "Trinity_Song": {
        "Tir": false,
        "Hamle": false,
        "Mesgana": false
      },
      "St_Mary_Song": {
        "Yekatit": false,
        "Nehase": false,
        "Mesgana": false
      },
      "K_Gebriel_Song": {
        "Tahsas": false,
        "Hamle": false,
        "Mesgana": false
      },
      "songLyrics": {
        "isShortSong": false,
        "shortLyrics": {
          "lyrics": "",
          "translation": ""
        },
        "longLyrics": {
          "chorus": "ተክለ ሀይማኖት ባህታዊ\nምድራዊ ሲሉ ሰማያዊ\nበአደባባዩ ተተክለሀል\nተክለአብ መልካሙን\nፍሬ አፍርተሀል",
          "verse": [
            "ቃል ኪዳን አለ የገነነ\nምሕረት የሚያሰጥ የታመነ\nበስምህ ውኃ አጠጥተህ\nዋጋችን በዝቷል አባታችን",
            "እኛም ሁነናል ልጆችህ\nማርኮ አስቀርቶን መግባርህ\nበምልጃህ ጸሎት ቱርፋት\nቤታችን ሞላ በረከት",
            "ምሕረት ይዘንባል ከሰማይ\nበአንድ እግርህ ቁመህ ስፀልይ\nብዙህ ተጋለህ አትርፈሃል\nያገለገልኸው አክብሮሃል",
            "ተሰባበሩ ጣዖታቱ\nአምነው ሰገዱ መኳንንቱ\nየበረታው ቃል ከአፍህ ወጥቶ\nየአምላክ አድርጓል ሁሉን ገዝቶ",
            "እኛም ሆነናል ልጆችህ\nማርኮ አስቀርቶን ምግባርህ\nበምልጃህ ጸሎት ትሩፋት\nቤታችን ሞላ በረከት",
            "",
            "",
            "",
            "",
            ""
          ]
        }
      }
    },
    {
      "id": "19",
      "Timestamp": 45866.68900798611,
      "Title": "ተክለ አብ ተክለወልድ ተክለ መንፈስ ቅዱስ",
      "singer": "ሌላ",
      "singerOther": "ጸዳለ ጎበዜ",
      "about": [
        "የቅዱሳን ጻድቃንና ሰማዕታት"
      ],
      "minor_holidays": [],
      "main_holidays": [],
      "angels": [],
      "Trinity_Song": {
        "Tir": false,
        "Hamle": false,
        "Mesgana": false
      },
      "St_Mary_Song": {
        "Yekatit": false,
        "Nehase": false,
        "Mesgana": false
      },
      "K_Gebriel_Song": {
        "Tahsas": false,
        "Hamle": false,
        "Mesgana": false
      },
      "songLyrics": {
        "isShortSong": false,
        "shortLyrics": {
          "lyrics": "",
          "translation": ""
        },
        "longLyrics": {
          "chorus": "ተክለአብ ተክለወልድ ተክለመንፈስቅዱስ\nበቤትህ ትከለኝ ጸድቄ ልቀደስ",
          "verse": [
            "ፍሬ ሃይማኖትን ከምግባር ደምሬ\nለመያዝ አልቻልኩም አቅቶኛል ዛሬ\nወደ አንተ እጮኻለሁ በምልጃህ ታምኜ\nበስምህ እንድጸድቅ ፈጣሪን ለምኜ",
            "ዘወትር ገድልህን በእምነት እሰማለሁ\nዕጣኑን ማዕጠንቱን እታጠነዋለሁ\nከሚያጠቃኝ ደዌ ከክፉ በሽታ\nእንድድን አድርጎ ይሰጠኛል ደስታ",
            "ከሱራፌል ተርታ ከመሃል ተገኝተህ\nጸሎቴን አሳርግ ልመናዬን ሰምተህ\nሥላሴ ከሰጡህ ሰማያዊ አዳራሽ\nተሳታፊ አድርገኝ የምሥጢር ተቋዳሽ",
            "",
            "",
            "",
            "",
            "",
            "",
            ""
          ]
        }
      }
    },
    {
      "id": "20",
      "Timestamp": 45869.442906365744,
      "Title": "ኀዲጎ ብእሲቶ",
      "singer": "ሌላ",
      "about": [
        "የቅዱሳን ጻድቃንና ሰማዕታት"
      ],
      "minor_holidays": [],
      "main_holidays": [],
      "angels": [],
      "Trinity_Song": {
        "Tir": false,
        "Hamle": false,
        "Mesgana": false
      },
      "St_Mary_Song": {
        "Yekatit": false,
        "Nehase": false,
        "Mesgana": false
      },
      "K_Gebriel_Song": {
        "Tahsas": false,
        "Hamle": false,
        "Mesgana": false
      },
      "songLyrics": {
        "isShortSong": true,
        "shortLyrics": {
          "lyrics": "ኀዲጎ ብእሲቶ መኒኖ መንግሥቶ /2/\nዘፈለሰ /3/ መኒኖ መንግሥቶ /2/",
          "translation": "ሚስቱንና መንግሥቱን ትቶ መነነ /ቅዱስ ገብረ ክርስቶስ/"
        },
        "longLyrics": {
          "chorus": "",
          "verse": [
            "",
            "",
            "",
            "",
            "",
            "",
            "",
            "",
            "",
            ""
          ]
        }
      }
    },
    {
      "id": "21",
      "Timestamp": 45868.670364791666,
      "Title": "ነዋ ጊዮርጊስ ",
      "singer": "ሌላ",
      "about": [
        "የቅዱሳን ጻድቃንና ሰማዕታት"
      ],
      "minor_holidays": [],
      "main_holidays": [],
      "angels": [],
      "Trinity_Song": {
        "Tir": false,
        "Hamle": false,
        "Mesgana": false
      },
      "St_Mary_Song": {
        "Yekatit": false,
        "Nehase": false,
        "Mesgana": false
      },
      "K_Gebriel_Song": {
        "Tahsas": false,
        "Hamle": false,
        "Mesgana": false
      },
      "songLyrics": {
        "isShortSong": true,
        "shortLyrics": {
          "lyrics": "ነዋ ጊዮርጊስ አሐዱ እም ቅዱሳን ሰማዕት /2/\nመጽአ ይርድአኒ ይቤ ምኒልክ ንጉሥ /2/",
          "translation": "ንጉሥ ምኒልክ አለ እነሆ ከቅዱሳን ሰማዕት አንድ የሆነ ጊዮርጊስ ሊረዳኝ መጣ"
        },
        "longLyrics": {
          "chorus": "",
          "verse": [
            "",
            "",
            "",
            "",
            "",
            "",
            "",
            "",
            "",
            ""
          ]
        }
      }
    },
    {
      "id": "22",
      "Timestamp": 45869.42850537037,
      "Title": "አልቦ እም ቅድሜሁ",
      "singer": "ሌላ",
      "about": [
        "የቅዱሳን ጻድቃንና ሰማዕታት"
      ],
      "minor_holidays": [],
      "main_holidays": [],
      "angels": [],
      "Trinity_Song": {
        "Tir": false,
        "Hamle": false,
        "Mesgana": false
      },
      "St_Mary_Song": {
        "Yekatit": false,
        "Nehase": false,
        "Mesgana": false
      },
      "K_Gebriel_Song": {
        "Tahsas": false,
        "Hamle": false,
        "Mesgana": false
      },
      "songLyrics": {
        "isShortSong": true,
        "shortLyrics": {
          "lyrics": "አልቦ እም ቅድሜሁ ወአልቦ እምድኅሬሁ ማኅሌታይ ሰብእ ዘከማሁ /2/\nያሬድ ካህን ይኬልህ ትንሣኤሁ ኢየአዱ እንስሳ ወሰብእ እምነ ሠላስ ዜማሁ /2/",
          "translation": "ከእርሱም በፊት ከእርሱም በኋላ እንደእሱ ማኅሌታይ ሰው የለም \nያሬድ ካህን ትንሣኤውን ይናገራል ሰውም እንሰሳም ከሦስት ዜማዎቹ አይወጣም"
        },
        "longLyrics": {
          "chorus": "",
          "verse": [
            "",
            "",
            "",
            "",
            "",
            "",
            "",
            "",
            "",
            ""
          ]
        }
      }
    },
    {
      "id": "23",
      "Timestamp": 45869.397563715276,
      "Title": "አማን በአማን ",
      "singer": "ሌላ",
      "about": [
        "የቅዱሳን ጻድቃንና ሰማዕታት"
      ],
      "minor_holidays": [],
      "main_holidays": [],
      "angels": [],
      "Trinity_Song": {
        "Tir": false,
        "Hamle": false,
        "Mesgana": false
      },
      "St_Mary_Song": {
        "Yekatit": false,
        "Nehase": false,
        "Mesgana": false
      },
      "K_Gebriel_Song": {
        "Tahsas": false,
        "Hamle": false,
        "Mesgana": false
      },
      "songLyrics": {
        "isShortSong": true,
        "shortLyrics": {
          "lyrics": "አማን በአማን /2/ ፀሐየ ልዳ /2/\nፀሐየ ልዳ ኮከብ ፋርስ /2/",
          "translation": "እዉነት ነዉ ቅዱስ ጊዮርጊስ የልዳ ፀሐይ የፋርስ ኮከን ነዉ "
        },
        "longLyrics": {
          "chorus": "",
          "verse": [
            "",
            "",
            "",
            "",
            "",
            "",
            "",
            "",
            "",
            ""
          ]
        }
      }
    },
    {
      "id": "24",
      "Timestamp": 45866.685820011575,
      "Title": "አረሳት ኢትዮጵያን",
      "singer": "ሊቀ መዘምራን ይልማ ኃይሉ",
      "about": [
        "የቅዱሳን ጻድቃንና ሰማዕታት"
      ],
      "minor_holidays": [],
      "main_holidays": [],
      "angels": [],
      "Trinity_Song": {
        "Tir": false,
        "Hamle": false,
        "Mesgana": false
      },
      "St_Mary_Song": {
        "Yekatit": false,
        "Nehase": false,
        "Mesgana": false
      },
      "K_Gebriel_Song": {
        "Tahsas": false,
        "Hamle": false,
        "Mesgana": false
      },
      "songLyrics": {
        "isShortSong": false,
        "shortLyrics": {
          "lyrics": "",
          "translation": ""
        },
        "longLyrics": {
          "chorus": "አረሳት ኢትዮጲያን በእርፈ መስቀል  \nአባ ተክለሃይማኖት ሰባኬ ወንጌል \nየእግዚአብሔር ሰው ነው ተወዳጅ በ ሰማይ \nየተረማመደ በጽድቅ አደባባይ  ",
          "verse": [
            "ፈውስና ጸሎቱ ቃሉ የተሰማ \nወንጌል  የሰበከ በገጠር ከተማ  \nየእቲሳው ኮከብ የደብረ አስቦቱ \nለወንጌል ተዋጋች ንጽሕት ሕይወቱ   ",
            "ፋናው እስከ ዛሬ ሲያበራ የኖረ \nየእቲሳው አባት ፍስሐጽዮን \nእግዚአርያ እናቱ ማሕፀነ ብሩክ \nወለደች  ኮከብን ሲዖልን የሚያውክ",
            "ዲያቢሎስ እስካሁን ስሙ ሲጠራበት \nሲረገጥ ይኖራል በእሳት  ሰንሰለት \nአዲስ  ሐዋርያ  የኢትዮጵያ አባት \nደጋ ና ቆላውን በመስቀል ባረካት",
            "ምንጩና ፏፏቴው ተራራው  ቅዱስ ነው\nየአባታችን መስቀል ጸሎት ስለነካው \nየተራመደበት የዳሰሰው ሁሉ \nድውይ ይፈውሳል ሳርና ቅጠሉ",
            "",
            "",
            "",
            "",
            "",
            ""
          ]
        }
      }
    },
    {
      "id": "25",
      "Timestamp": 45869.439758622684,
      "Title": "አረጋዊ ምሉዓ ፍቅር",
      "singer": "ሌላ",
      "about": [
        "የቅዱሳን ጻድቃንና ሰማዕታት"
      ],
      "minor_holidays": [],
      "main_holidays": [],
      "angels": [],
      "Trinity_Song": {
        "Tir": false,
        "Hamle": false,
        "Mesgana": false
      },
      "St_Mary_Song": {
        "Yekatit": false,
        "Nehase": false,
        "Mesgana": false
      },
      "K_Gebriel_Song": {
        "Tahsas": false,
        "Hamle": false,
        "Mesgana": false
      },
      "songLyrics": {
        "isShortSong": true,
        "shortLyrics": {
          "lyrics": "አረጋዊ ምሉዓ ፍቅር ከመ ጽጌረዳ ዘይወፅእ እም አፉሁ ዕጣነ ቅድስና /2/\nለገቢረ ሠናይ ዘይወጽዕ ከመ ማይ ምስለ ገብረ ክርስቶስ /2/",
          "translation": "ከአንደበቱ እንደ ጽጌረዳ የቅድስና መልካም ሽታ /ቃል/ \nየሚወጣ ፍቅርን የተመላ አረጋዊ ከገብረ ክርስቶስ ጋር \nለበጎ ሥራ አንደ ውኃ ይወጣል"
        },
        "longLyrics": {
          "chorus": "",
          "verse": [
            "",
            "",
            "",
            "",
            "",
            "",
            "",
            "",
            "",
            ""
          ]
        }
      }
    },
    {
      "id": "26",
      "Timestamp": 45869.59547188657,
      "Title": "አርሴማ ቅድስት",
      "singer": "ሌላ",
      "about": [
        "የቅዱሳን ጻድቃንና ሰማዕታት"
      ],
      "minor_holidays": [],
      "main_holidays": [],
      "angels": [],
      "Trinity_Song": {
        "Tir": false,
        "Hamle": false,
        "Mesgana": false
      },
      "St_Mary_Song": {
        "Yekatit": false,
        "Nehase": false,
        "Mesgana": false
      },
      "K_Gebriel_Song": {
        "Tahsas": false,
        "Hamle": false,
        "Mesgana": false
      },
      "songLyrics": {
        "isShortSong": true,
        "shortLyrics": {
          "lyrics": "አርሴማ ቅድስት /2/ ወሰማዕት /2/\nወሰማዕት /5/ አርሴማ ቅድስት /2/",
          "translation": "አርሴማ ቅድስት ሰማዕት ምስክር ናት"
        },
        "longLyrics": {
          "chorus": "",
          "verse": [
            "",
            "",
            "",
            "",
            "",
            "",
            "",
            "",
            "",
            ""
          ]
        }
      }
    },
    {
      "id": "27",
      "Timestamp": 45869.59422261574,
      "Title": "አርሴማ ቅድስት ሰማዕት",
      "singer": "ሌላ",
      "about": [
        "የቅዱሳን ጻድቃንና ሰማዕታት"
      ],
      "minor_holidays": [],
      "main_holidays": [],
      "angels": [],
      "Trinity_Song": {
        "Tir": false,
        "Hamle": false,
        "Mesgana": false
      },
      "St_Mary_Song": {
        "Yekatit": false,
        "Nehase": false,
        "Mesgana": false
      },
      "K_Gebriel_Song": {
        "Tahsas": false,
        "Hamle": false,
        "Mesgana": false
      },
      "songLyrics": {
        "isShortSong": false,
        "shortLyrics": {
          "lyrics": "",
          "translation": ""
        },
        "longLyrics": {
          "chorus": "አርሴማ አርሴማ ቅድስት ሰማዕት /2/\nሞገስ አግኝተሻል በክርስቶስ ፊት",
          "verse": [
            "አርሴማ ታምርሽ ልዩ ነው\n\"       \" ገድልሽ አስደናቂ \n\"       \" ስምሽ ብርሃን ነው\n\"       \" ማለዳ ፈንጣቂ",
            "አርሴማ ስምሽን እየጠራ\n\"       \" ጠግቧል የተራበው\n\"       \" ምስኪኑም ዘመረ\n\"       \" ባንቺ አልፎ መከራው",
            "አርሴማ ፅኑ ነው ኪዳንሽ\n\"       \" የተሰጠሽ ከአምላክ\n\"       \" በአይኔ አይቻለው\n\"       \" ጠላት ሲንበረከክ",
            "አርሴማ ዓለም ይስማው ዛሬ\n\"       \" ዜና ተጋድሎሽን\n\"       \" ይገረም ይደነቅ\n\"       \" ይመስክር ዝናሽን",
            "",
            "",
            "",
            "",
            "",
            ""
          ]
        }
      }
    },
    {
      "id": "28",
      "Timestamp": 45869.42449520833,
      "Title": "አሰርገዋ ",
      "singer": "ሌላ",
      "singerOther": "ተክለ ሳዊሮስ ሰ/ት/ቤት",
      "about": [
        "የቅዱሳን ጻድቃንና ሰማዕታት"
      ],
      "minor_holidays": [],
      "main_holidays": [],
      "angels": [],
      "Trinity_Song": {
        "Tir": false,
        "Hamle": false,
        "Mesgana": false
      },
      "St_Mary_Song": {
        "Yekatit": false,
        "Nehase": false,
        "Mesgana": false
      },
      "K_Gebriel_Song": {
        "Tahsas": false,
        "Hamle": false,
        "Mesgana": false
      },
      "songLyrics": {
        "isShortSong": true,
        "shortLyrics": {
          "lyrics": "አሰርገዋ ለኢትዮጵያ በስብሐት ወበ ሃሌ ሉያ /2/ \nያሬድ ካህን ጥዑመ ልሳን ለቤተክርስቲያን ፀሐያ /2/ ",
          "translation": "አሸበረቃት ኢትዮጵያን በምስጋና ወበ ሃሌ ሉያ /2/ \nካህኑ ያሬድ ልሳኑ ጣፋጭ ለቤተ ክርስቲያን ብርሃኗ/2/"
        },
        "longLyrics": {
          "chorus": "",
          "verse": [
            "",
            "",
            "",
            "",
            "",
            "",
            "",
            "",
            "",
            ""
          ]
        }
      }
    },
    {
      "id": "29",
      "Timestamp": 45866.687094050925,
      "Title": "አባ አቡነ",
      "singer": "ሌላ",
      "about": [
        "የቅዱሳን ጻድቃንና ሰማዕታት"
      ],
      "minor_holidays": [],
      "main_holidays": [],
      "angels": [],
      "Trinity_Song": {
        "Tir": false,
        "Hamle": false,
        "Mesgana": false
      },
      "St_Mary_Song": {
        "Yekatit": false,
        "Nehase": false,
        "Mesgana": false
      },
      "K_Gebriel_Song": {
        "Tahsas": false,
        "Hamle": false,
        "Mesgana": false
      },
      "songLyrics": {
        "isShortSong": true,
        "shortLyrics": {
          "lyrics": "አባ አቡነ አባ መምህርነ /2/ መምህርነ አባ ተክለ ሃይማኖት /2/\nእም አእላፍ /2/ ኅሩይ ተክለሃይማኖት /2/",
          "translation": ""
        },
        "longLyrics": {
          "chorus": "",
          "verse": [
            "",
            "",
            "",
            "",
            "",
            "",
            "",
            "",
            "",
            ""
          ]
        }
      }
    },
    {
      "id": "30",
      "Timestamp": 45857.44941292824,
      "Title": "ኢትዮጵያዊ ሱራፊ",
      "singer": "ሌላ",
      "singerOther": "በደብረ ታቦር ፍኖተ ሕይወት ሰ/ት/ቤት",
      "about": [
        "የቅዱሳን ጻድቃንና ሰማዕታት"
      ],
      "minor_holidays": [],
      "main_holidays": [],
      "angels": [],
      "Trinity_Song": {
        "Tir": false,
        "Hamle": false,
        "Mesgana": false
      },
      "St_Mary_Song": {
        "Yekatit": false,
        "Nehase": false,
        "Mesgana": false
      },
      "K_Gebriel_Song": {
        "Tahsas": false,
        "Hamle": false,
        "Mesgana": false
      },
      "songLyrics": {
        "isShortSong": false,
        "shortLyrics": {
          "lyrics": "",
          "translation": ""
        },
        "longLyrics": {
          "chorus": "ኢትዮጵያዊ ሱራፊ ተክለሃይማኖት\nእስመ ነቢይ ወሐዋርያ\nዘተፈነውከ ውስተ ምድርነ",
          "verse": [
            "ሥጋ መለኮትን ለሰዉት እጆችህ\nደመ መለኮትን ለቀዱ ጣቶችህ\nለታጠቅከው ቅናት ለደረብከው ካባ\nሰላም እንላለን ባርከነ አባ",
            "ተክለ አብ ተክለ ወልድ ተክለ መንፈስቅዱስ\nየሕግ መምህር ኢትዮጲያዊ ጳውሎስ\nብጹዕ ሐዋርያ የአምላክ አገልጋይ\nወንጌልን በምድር ቅዳሴን በሰማይ",
            "ኢትዮጲያዊ ሱራፊ በምድር ላይ መልአክ\nመንበረ ሥላሴን በማዕጠንት ያጠንክ\nአእራጌ ጸሎት ሰማያዊ ካህን\nሰባኬ ሃይማኖት በሃይማኖት አጽናን",
            "",
            "",
            "",
            "",
            "",
            "",
            ""
          ]
        }
      }
    },
    {
      "id": "31",
      "Timestamp": 45869.4091952662,
      "Title": "እም ገዳመ መንበሩ ",
      "singer": "ሌላ",
      "about": [
        "የቅዱሳን ጻድቃንና ሰማዕታት"
      ],
      "minor_holidays": [],
      "main_holidays": [],
      "angels": [],
      "Trinity_Song": {
        "Tir": false,
        "Hamle": false,
        "Mesgana": false
      },
      "St_Mary_Song": {
        "Yekatit": false,
        "Nehase": false,
        "Mesgana": false
      },
      "K_Gebriel_Song": {
        "Tahsas": false,
        "Hamle": false,
        "Mesgana": false
      },
      "songLyrics": {
        "isShortSong": true,
        "shortLyrics": {
          "lyrics": "እም ገዳመ መንበሩ /2/ ደብረ ዝቋላ ማኅደሩ/2/ \nለመካነ ሕይወት/3/ ይዕቲ ማኅደሩ/2/ ",
          "translation": "ከገዳም/ከበረሃ/ መቀመጫው በበረሃ ማደሪያው የ ዝቋላ ተራራ ነው፡፡ይቺም የሕይወት ቦታ ናት"
        },
        "longLyrics": {
          "chorus": "",
          "verse": [
            "",
            "",
            "",
            "",
            "",
            "",
            "",
            "",
            "",
            ""
          ]
        }
      }
    },
    {
      "id": "32",
      "Timestamp": 45869.606809675926,
      "Title": "እስጢፍኖስ ሰማዕት",
      "singer": "ሌላ",
      "about": [
        "የቅዱሳን ጻድቃንና ሰማዕታት"
      ],
      "minor_holidays": [],
      "main_holidays": [],
      "angels": [],
      "Trinity_Song": {
        "Tir": false,
        "Hamle": false,
        "Mesgana": false
      },
      "St_Mary_Song": {
        "Yekatit": false,
        "Nehase": false,
        "Mesgana": false
      },
      "K_Gebriel_Song": {
        "Tahsas": false,
        "Hamle": false,
        "Mesgana": false
      },
      "songLyrics": {
        "isShortSong": true,
        "shortLyrics": {
          "lyrics": "እስጢፍኖስ ሰማዕት ሊቀ ዲያቆናት ለምዕመናን የተሾምክ /2/\nየአምላክህን ትዕዛዝ በሥራ የፈፀምክ /2/",
          "translation": ""
        },
        "longLyrics": {
          "chorus": "",
          "verse": [
            "",
            "",
            "",
            "",
            "",
            "",
            "",
            "",
            "",
            ""
          ]
        }
      }
    },
    {
      "id": "33",
      "Timestamp": 45869.6079774074,
      "Title": "እንዘ ይነብር በየማኑ",
      "singer": "ሌላ",
      "about": [
        "የቅዱሳን ጻድቃንና ሰማዕታት"
      ],
      "minor_holidays": [],
      "main_holidays": [],
      "angels": [],
      "Trinity_Song": {
        "Tir": false,
        "Hamle": false,
        "Mesgana": false
      },
      "St_Mary_Song": {
        "Yekatit": false,
        "Nehase": false,
        "Mesgana": false
      },
      "K_Gebriel_Song": {
        "Tahsas": false,
        "Hamle": false,
        "Mesgana": false
      },
      "songLyrics": {
        "isShortSong": true,
        "shortLyrics": {
          "lyrics": "እንዘ ይነብር ለአብ በየማኑ ወይረፍቅ ውስተ ህፅኑ የማኑ ለአብ /2/\nርዕየ ወልደ ርዕየ በዓይኑ/እስጢፋኖስ/2/ ምሉዓ ጥበብ /2/",
          "translation": "ጥበብን የተሞላ እስጢፋኖስ ወልድን በአብ ቀኝ ተቀምጦ በአብ እቅፍ/ዕሪና/ሲመሰገን በዓይኑ አየው"
        },
        "longLyrics": {
          "chorus": "",
          "verse": [
            "",
            "",
            "",
            "",
            "",
            "",
            "",
            "",
            "",
            ""
          ]
        }
      }
    },
    {
      "id": "34",
      "Timestamp": 45869.406064675924,
      "Title": "ኦ ፍጡነ ረድኤት ",
      "singer": "ሌላ",
      "about": [
        "የቅዱሳን ጻድቃንና ሰማዕታት"
      ],
      "minor_holidays": [],
      "main_holidays": [],
      "angels": [],
      "Trinity_Song": {
        "Tir": false,
        "Hamle": false,
        "Mesgana": false
      },
      "St_Mary_Song": {
        "Yekatit": false,
        "Nehase": false,
        "Mesgana": false
      },
      "K_Gebriel_Song": {
        "Tahsas": false,
        "Hamle": false,
        "Mesgana": false
      },
      "songLyrics": {
        "isShortSong": false,
        "shortLyrics": {
          "lyrics": "",
          "translation": ""
        },
        "longLyrics": {
          "chorus": "ኦ ፍጡነ ረድኤት /2/\nየእግዚአብሔር አገልጋይ ሊቀ /ቅዱስ/ ሰማዕት /2/",
          "verse": [
            "ሰላም ላንተ ይሁን ፍጡነ ረድኤት\nየልዳው ፀሐይ ፍጡነ ረድኤት\nበጨካኝ ንጉሥ ፊት ቆምክ አደባባይ\nታማኝ አገልጋይ ነህ ፍጡነ ረድኤት\nስቃይ ያልበገረህ ፍጡነ ረድኤት\nአክሊልን አገኘህ መከራን ታግሠህ ",
            "የፈጣሪውን ስም ፍጡነ ረድኤት\nስለመሰከረ ፍጡነ ረድኤት\nጊዮርጊስ ሰማዕት በሰይፍ ተመተረ\nየስቃይ መሣሪያ ፍጡነ ረድኤት\nያላዘናጋህ ፍጡነ ረድኤት\nመንፈሳዊ አርበኛ ጊዮርጊስ አንተ ነህ ",
            "ለእምነቱ ተጋዳይ ፍጡነ ረድኤት\nታማኝ ወታደር ፍጡነ ረድኤት\nቢነገር አያልቅም የተሰጠህ ክብር\nስቃይ ቢያደርሱብህ ፍጡነ ረድኤት\nበመታገሥህ ፍጡነ ረድኤት\nሲወሳ ይኖራል ዘለዓለም ስምህ ",
            "ለሰማው ይደንቃል ፍጡነ ረድኤት\nየአንተ ሰማዕትነት ፍጡነ ረድኤት\nምሳሌ ይሆናል ለሁሉ ፍጥረት\nገድልህ ይናገራል ፍጡነ ረድኤት\nክብር እንደተሰጠህ ፍጡነ ረድኤት\nጊዜ የማይሽረው ምግባር ሃይማኖት ",
            "",
            "",
            "",
            "",
            "",
            ""
          ]
        }
      }
    },
    {
      "id": "35",
      "Timestamp": 45869.44158244213,
      "Title": "ከመ ኖኅ ",
      "singer": "ሌላ",
      "about": [
        "የቅዱሳን ጻድቃንና ሰማዕታት"
      ],
      "minor_holidays": [],
      "main_holidays": [],
      "angels": [],
      "Trinity_Song": {
        "Tir": false,
        "Hamle": false,
        "Mesgana": false
      },
      "St_Mary_Song": {
        "Yekatit": false,
        "Nehase": false,
        "Mesgana": false
      },
      "K_Gebriel_Song": {
        "Tahsas": false,
        "Hamle": false,
        "Mesgana": false
      },
      "songLyrics": {
        "isShortSong": true,
        "shortLyrics": {
          "lyrics": "ከመ ኖኅ በየውሀቱ ወከመ ኢዮብ በትእግሥቱ ገብረ ክርስቶስ/2/ \nወከመ ኤልያስ/2/ ይመስል ሕይወቱ ለአረጋዊ/2/ ",
          "translation": "እንደ ኖኅ ነው በየውሐቱ እንደ ኢዮብም ነው በትእግሥቱ ገብረ ክርስቶስ/2/ \nእንደ ኤልያስም /2/ ይመስላል ሕይወቱ የአረጋዊ/2/"
        },
        "longLyrics": {
          "chorus": "",
          "verse": [
            "",
            "",
            "",
            "",
            "",
            "",
            "",
            "",
            "",
            ""
          ]
        }
      }
    },
    {
      "id": "36",
      "Timestamp": 45868.67144358796,
      "Title": "ከመ ጸበል ዘነፋስ ",
      "singer": "ሌላ",
      "about": [
        "የቅዱሳን ጻድቃንና ሰማዕታት"
      ],
      "minor_holidays": [],
      "main_holidays": [],
      "angels": [],
      "Trinity_Song": {
        "Tir": false,
        "Hamle": false,
        "Mesgana": false
      },
      "St_Mary_Song": {
        "Yekatit": false,
        "Nehase": false,
        "Mesgana": false
      },
      "K_Gebriel_Song": {
        "Tahsas": false,
        "Hamle": false,
        "Mesgana": false
      },
      "songLyrics": {
        "isShortSong": true,
        "shortLyrics": {
          "lyrics": "ከመ ጸበል ዘነፋስ ዘረውዎ ደብረ ይድራስ /2/\nለብጹዕ ወለቅዱስ ቅዱስ ቅዱስ ጊዮርጊስ ሰማዕት /2/",
          "translation": "እንደ ነፋስ ትቢያ በተኑት በይድራስ ተራራ /2/\nብጹዑንና ምስጉኑን ምስጉን ምስጉን ጊዮርጊስ ሰማዕት /2/"
        },
        "longLyrics": {
          "chorus": "",
          "verse": [
            "",
            "",
            "",
            "",
            "",
            "",
            "",
            "",
            "",
            ""
          ]
        }
      }
    },
    {
      "id": "37",
      "Timestamp": 45869.39884715278,
      "Title": "ኮከብ ሲወጣ አየን ",
      "singer": "ሌላ",
      "singerOther": "ፍቃዱ አማረ",
      "about": [
        "የቅዱሳን ጻድቃንና ሰማዕታት"
      ],
      "minor_holidays": [],
      "main_holidays": [],
      "angels": [],
      "Trinity_Song": {
        "Tir": false,
        "Hamle": false,
        "Mesgana": false
      },
      "St_Mary_Song": {
        "Yekatit": false,
        "Nehase": false,
        "Mesgana": false
      },
      "K_Gebriel_Song": {
        "Tahsas": false,
        "Hamle": false,
        "Mesgana": false
      },
      "songLyrics": {
        "isShortSong": false,
        "shortLyrics": {
          "lyrics": "",
          "translation": ""
        },
        "longLyrics": {
          "chorus": "ኮከብ ሲወጣ አየን በልዳ ሰማይ\nኃያሉ ጊዮርጊስ ቆሟል ዘንዶው ላይ\nቤሩታዊት ተነሽ አትሞችም ተጽናኚ\nአውሬው ተሸንፏል በአምላክሽ እመኚ",
          "verse": [
            "ሕዝቡን የሚያስጨንቅ ሰው ገብሩኝ ብሎ\nጊዮርጊስ አደቀቀው በእግሮቹ ሥር ጥሎ\nየንጉሡ ልጅ ቤሩት ዕጣው ለአንቺ ሆኗል\nከግንዱ ሊፈታሽ ፈረሰኛው ቆሟል",
            "በጣዖታት ምድር አዲስ ፀሐይ ወጣ\nበጽድቅ እያበራ ጊዮርጊስ ታጥቆ መጣ\nእንግዲህ አጵሎን አቴና ሆይ እፈር\nምድሪቱን ይገዛል የአምላካችን ክብር",
            "ዱድያኖስ መንግሥቱን አልቻለም ሊያጸና\nታላቁ ሰማዕት ቅጥሩን ሰብሯልና\nበአነገበው መስቀል አምላኩን ገለጸ\nየድል በፍታን ለብሶ ጭፍሮቹን ገሠጸ",
            "በይድራስ ተራራ ቅኔን ያስተማረ\nድንቅ ነው አጥንቱ በኃይል የከበረ\nተአምራቱ በዝቶ ገድሉን ደመደመ\nበጸጋው ቃል ኪዳን ትውልዱን ጠቀመ",
            "",
            "",
            "",
            "",
            "",
            ""
          ]
        }
      }
    },
    {
      "id": "38",
      "Timestamp": 45869.408181990744,
      "Title": "ኮከብ ብሩህ ",
      "singer": "ሌላ",
      "about": [
        "የቅዱሳን ጻድቃንና ሰማዕታት"
      ],
      "minor_holidays": [],
      "main_holidays": [],
      "angels": [],
      "Trinity_Song": {
        "Tir": false,
        "Hamle": false,
        "Mesgana": false
      },
      "St_Mary_Song": {
        "Yekatit": false,
        "Nehase": false,
        "Mesgana": false
      },
      "K_Gebriel_Song": {
        "Tahsas": false,
        "Hamle": false,
        "Mesgana": false
      },
      "songLyrics": {
        "isShortSong": true,
        "shortLyrics": {
          "lyrics": "ኮከብ ብሩህ ገብረ መንፈስ ቅዱስ ዘሠረቀ እም አቅሌስያ ቤተ ክርስቲያን ዘንሰምያ /2/\nኮኖሙ አበ ለሰብአ ግብፅ ወኢትዮጵያ አማን ገብረ መንፈስቅዱስ ሐዋርያ /2/",
          "translation": "ቤተ ክርስቲያን ብለን ከምንጠራት ከአቅሌስያ የወጣ ብሩህ ኮከብ ለግብፅና ለኢትዮጵያ ሰዎች አባት ሆናቸው በእውነት ገብረ መንፈስ ቅዱስ ሐዋርያ"
        },
        "longLyrics": {
          "chorus": "",
          "verse": [
            "",
            "",
            "",
            "",
            "",
            "",
            "",
            "",
            "",
            ""
          ]
        }
      }
    },
    {
      "id": "39",
      "Timestamp": 45866.5942046412,
      "Title": "ወይቤሎሙ ሑሩ",
      "singer": "ማሕበረ ቅዱሳን",
      "about": [
        "የቅዱሳን ጻድቃንና ሰማዕታት"
      ],
      "minor_holidays": [],
      "main_holidays": [],
      "angels": [],
      "Trinity_Song": {
        "Tir": false,
        "Hamle": false,
        "Mesgana": false
      },
      "St_Mary_Song": {
        "Yekatit": false,
        "Nehase": false,
        "Mesgana": false
      },
      "K_Gebriel_Song": {
        "Tahsas": false,
        "Hamle": false,
        "Mesgana": false
      },
      "songLyrics": {
        "isShortSong": false,
        "shortLyrics": {
          "lyrics": "",
          "translation": ""
        },
        "longLyrics": {
          "chorus": "ወይቤሎሙ ሑሩ ወመሀሩ ለዘየአምን\nወንጌለ መንግሥተ ሰማያት /2/",
          "verse": [
            "በሕይወታችሁ ስበኩ በኑሯችሁ ከጽንፍ እስከ ጽንፍ\nበዓለም ዙሪያ አዳርሱ ሳትሰለቹ ደመና ጠቅሳችሁ እንደ ወፍ",
            "በኃጢአት ገመድ ተይዞ ለታሰረው\nበዓለም ጽልመት ለተዋጠው\nየእውነት መንገድ ብርሃኑ ለጠፋበት\nበሁለንተናው ፈንጥቁበት",
            "የጽድቅ እንጀራ በማጣት ለተራበው\nየሕይወትን ውኃ ለተጠማው\nቀቢጸ ተስፋ በልቡ ላደረበት\nየወንጌል ማዕድ አቅርቡለት",
            "አርድተ ወንጌል ካህናት ሊቃውንት ለተልእኮ የጠራችሁ\nከእውነተኛው ምንጭ ከጌታን ከባዕሉ የሕይወትን ውኃ የጠጣችሁ",
            "ሁለንተናችሁ ይነበብ ፊደል ይሁን በትእዛዙ እየሄዳችሁ\nሥራችሁ ይብራ በዓለም እንደ ሻማ በሕይወታችሁ ሰብካችሁ",
            "",
            "",
            "",
            "",
            ""
          ]
        }
      }
    },
    {
      "id": "40",
      "Timestamp": 45869.429210312504,
      "Title": "ዘእምደብረ ደናግል ",
      "singer": "ሌላ",
      "about": [
        "የቅዱሳን ጻድቃንና ሰማዕታት"
      ],
      "minor_holidays": [],
      "main_holidays": [],
      "angels": [],
      "Trinity_Song": {
        "Tir": false,
        "Hamle": false,
        "Mesgana": false
      },
      "St_Mary_Song": {
        "Yekatit": false,
        "Nehase": false,
        "Mesgana": false
      },
      "K_Gebriel_Song": {
        "Tahsas": false,
        "Hamle": false,
        "Mesgana": false
      },
      "songLyrics": {
        "isShortSong": true,
        "shortLyrics": {
          "lyrics": "ዘእምደብረ /2/ ደናግል/2/ አባ አረጋዊ/2/ \nአረጋዊ ዘውገ ሙሴ ወገብረ ክርስቶስ አማን ቀደሶሙ መንፈስ ቅዱስ/2/",
          "translation": "ከደናግል ተራራ አባ አረጋዊ ሙሴ ገብረ ክርስቶስ ጓደኛሞች ናቸው፤በሥራቸው በምግባራቸው አንድ የሆኑ በእውነት መንፈስ ቅዱስ የቀደሳቸው ናቸው፡፡ "
        },
        "longLyrics": {
          "chorus": "",
          "verse": [
            "",
            "",
            "",
            "",
            "",
            "",
            "",
            "",
            "",
            ""
          ]
        }
      }
    },
    {
      "id": "41",
      "Timestamp": 45869.42963287037,
      "Title": "ዛ አንቀጽ ",
      "singer": "ሌላ",
      "about": [
        "የቅዱሳን ጻድቃንና ሰማዕታት"
      ],
      "minor_holidays": [],
      "main_holidays": [],
      "angels": [],
      "Trinity_Song": {
        "Tir": false,
        "Hamle": false,
        "Mesgana": false
      },
      "St_Mary_Song": {
        "Yekatit": false,
        "Nehase": false,
        "Mesgana": false
      },
      "K_Gebriel_Song": {
        "Tahsas": false,
        "Hamle": false,
        "Mesgana": false
      },
      "songLyrics": {
        "isShortSong": true,
        "shortLyrics": {
          "lyrics": "ዛ አንቀጽ እንተ እግዚአብሔር አንቀጸ አድኅኖ/2/ \nጻድቃን ይበውኡ ውስቴታ አረጋዊ ወገብረ ክርስቶስ/2/ ",
          "translation": "ይህች የእግዚአብሔር ደጅ ናት የድኅነት በር ናት ጻድቃን ወደሷ ይገባሉ አረጋዊና ገብረክርስቶስ፡፡ "
        },
        "longLyrics": {
          "chorus": "",
          "verse": [
            "",
            "",
            "",
            "",
            "",
            "",
            "",
            "",
            "",
            ""
          ]
        }
      }
    },
    {
      "id": "42",
      "Timestamp": 45869.427311990745,
      "Title": "ዜኖኩ ጽድቀከ ",
      "singer": "ሌላ",
      "about": [
        "የቅዱሳን ጻድቃንና ሰማዕታት"
      ],
      "minor_holidays": [],
      "main_holidays": [],
      "angels": [],
      "Trinity_Song": {
        "Tir": false,
        "Hamle": false,
        "Mesgana": false
      },
      "St_Mary_Song": {
        "Yekatit": false,
        "Nehase": false,
        "Mesgana": false
      },
      "K_Gebriel_Song": {
        "Tahsas": false,
        "Hamle": false,
        "Mesgana": false
      },
      "songLyrics": {
        "isShortSong": true,
        "shortLyrics": {
          "lyrics": "ዜኖኩ ጽድቀከ ወነገርኩ አድኅኖተከ ከሠትኩ ቃላቲከ ለሕዝብከ ኢትዮጵያ /2/\nበጸጋሁ ለመንፈስ ቅዱስ ወመሀርክዎሙ አነ ይቤ ያሬድ ካህን /2/",
          "translation": "ጽድቅህን ነገርኩኝ አዳኝነትህን አስተማርኩኝ ቃላትህን ለኢትዮጵያ ሕዝብ ነገርኩኝ /2/\nእኔም በመንፈስ ቅዱስ ጸጋ አስተማርኳቸው አለ ያሬድ ካህን /2/"
        },
        "longLyrics": {
          "chorus": "",
          "verse": [
            "",
            "",
            "",
            "",
            "",
            "",
            "",
            "",
            "",
            ""
          ]
        }
      }
    },
    {
      "id": "43",
      "Timestamp": 45859.58985508102,
      "Title": "የሕይወትን መዝገብ ",
      "singer": "ማሕበረ ቅዱሳን",
      "about": [
        "የቅዱሳን ጻድቃንና ሰማዕታት"
      ],
      "minor_holidays": [],
      "main_holidays": [],
      "angels": [],
      "Trinity_Song": {
        "Tir": false,
        "Hamle": false,
        "Mesgana": false
      },
      "St_Mary_Song": {
        "Yekatit": false,
        "Nehase": false,
        "Mesgana": false
      },
      "K_Gebriel_Song": {
        "Tahsas": false,
        "Hamle": false,
        "Mesgana": false
      },
      "songLyrics": {
        "isShortSong": false,
        "shortLyrics": {
          "lyrics": "",
          "translation": ""
        },
        "longLyrics": {
          "chorus": "የሕይወትን መዝገብ ቃሉን ያስነበቡህ\nየተዋሕዶ አርበኞች ቅዱሳን ዋኖችህ\nየድካም ዋጋቸው የእምነታቸው ፍሬ\nያማረ ነውና ምሰላቸው ዛሬ",
          "verse": [
            "ምሥጢሩ ምንድነው ድል የማድረጋቸው\nለሰማያዊ ክብር ለአክሊል ያበቃቸው\nየሕይወታቸውን መዝገብ ግለጥና አንብበው\nመፍትሔ አለውና ገድላቸው የአበው",
            "ድካም ሲበረታ በመንፈስ ስትዝል\nዙርያህን ሲከብህ የኃጢአት ማዕበል\nጽናት ትእግሥት አጥተህ እንዳትሰናከል\nበጾም ጸሎት በርታ አባቶችን ምሰል",
            "ዓለም ኢያሪኮ ቢፈትንህ ሥጋህ\nዲያብሎስም ቢያሤር ከመንገድ ሊያርቅህ\nልትወድቅ አትችልም ምን ቢያይል ፈተና\nካሰብክ የፀኑትን የተዋሕዶን ፋና",
            "",
            "",
            "",
            "",
            "",
            "",
            ""
          ]
        }
      }
    },
    {
      "id": "44",
      "Timestamp": 45869.59617842593,
      "Title": "የምዕመናን አባት",
      "singer": "ሌላ",
      "about": [
        "የቅዱሳን ጻድቃንና ሰማዕታት"
      ],
      "minor_holidays": [],
      "main_holidays": [],
      "angels": [],
      "Trinity_Song": {
        "Tir": false,
        "Hamle": false,
        "Mesgana": false
      },
      "St_Mary_Song": {
        "Yekatit": false,
        "Nehase": false,
        "Mesgana": false
      },
      "K_Gebriel_Song": {
        "Tahsas": false,
        "Hamle": false,
        "Mesgana": false
      },
      "songLyrics": {
        "isShortSong": true,
        "shortLyrics": {
          "lyrics": "የምዕመናን አባት አገልጋይ የአምላክ ባለሟል መርቆሬዎስ /2/\nተቀበለ ዛሬ /4/ አክሊለ ሰማዕታት /2/",
          "translation": ""
        },
        "longLyrics": {
          "chorus": "",
          "verse": [
            "",
            "",
            "",
            "",
            "",
            "",
            "",
            "",
            "",
            ""
          ]
        }
      }
    },
    {
      "id": "45",
      "Timestamp": 45857.44017158565,
      "Title": "የዓለሙን ክብር",
      "singer": "ማሕበረ ቅዱሳን",
      "about": [
        "የቅዱሳን ጻድቃንና ሰማዕታት"
      ],
      "minor_holidays": [],
      "main_holidays": [],
      "angels": [],
      "Trinity_Song": {
        "Tir": false,
        "Hamle": false,
        "Mesgana": false
      },
      "St_Mary_Song": {
        "Yekatit": false,
        "Nehase": false,
        "Mesgana": false
      },
      "K_Gebriel_Song": {
        "Tahsas": false,
        "Hamle": false,
        "Mesgana": false
      },
      "songLyrics": {
        "isShortSong": false,
        "shortLyrics": {
          "lyrics": "",
          "translation": ""
        },
        "longLyrics": {
          "chorus": "የዓለሙን ክብር ተድላውን መንነው\nለአንዲት ሃይማኖት ግፍን ተቀብለው\nሞተዋልና ስለ ስሙ ብለው /2/",
          "verse": [
            "ሞት በሌለባት ምድር በዚያች ይኖራሉ\n በማያልፍ ክብር ደምቀው ያበራሉ \n ቅዱሳኑ ወዳጆቹ ሁሉ ",
            "ከቶ ያልረገጣት የአመጻ እግር\nየሰው ዓይን ያላያት አዲሲቷን ምድር\nአወረሳቸው እግዚአብሔር /2/",
            "አመጸኛ ትውልድ በእምነቱ ያልጸና\nምንም አይገባባት ቢጎመጅስ ቢቀና\nአምላክ ለተገፉት ሠርቷታልና\nእምላክ ለቅዱሳን መርጧታልና",
            "ስለ ቅዱስ ራችሁሙ ስለ ፍቅሩ ብለው\nመራራውን ስቃይ ስላለፉት ችለው\nሞት የሌለባት ምድር አወረሳቸው /2/",
            "",
            "",
            "",
            "",
            "",
            ""
          ]
        }
      }
    },
    {
      "id": "46",
      "Timestamp": 45869.40998678241,
      "Title": "የዝቋላው ኮከብ ",
      "singer": "ሌላ",
      "singerOther": "ፀዳለ ጎበዜ ",
      "about": [
        "የቅዱሳን ጻድቃንና ሰማዕታት"
      ],
      "minor_holidays": [],
      "main_holidays": [],
      "angels": [],
      "Trinity_Song": {
        "Tir": false,
        "Hamle": false,
        "Mesgana": false
      },
      "St_Mary_Song": {
        "Yekatit": false,
        "Nehase": false,
        "Mesgana": false
      },
      "K_Gebriel_Song": {
        "Tahsas": false,
        "Hamle": false,
        "Mesgana": false
      },
      "songLyrics": {
        "isShortSong": false,
        "shortLyrics": {
          "lyrics": "",
          "translation": ""
        },
        "longLyrics": {
          "chorus": "የዝቋላው ኮከብ መፍቀሬ ጸሎት ወፆም /2/\nገብረመንፈስቅዱስ እንቁ ለገዳም\nቅረበነ /2/ ንዓ በሰላም ",
          "verse": [
            "እንደ ሰው ያይደል ኑሮህ ነው የመላእክት\nትጉህ መስተጋድል ገዳማዊ መብራት\nስምህ የከበረ በፈጣሪ አንደበት\nየገድልህ መዓዛ እንደ እጣን የሚሸት",
            "የእርሱን ቅድስና ዝቋላ መስክሪ\nእንደ ዓሣ በባህር ኖረ ብለሽ አውሪ\nኢትዮጵያም ትናገር የአንተን ታላቅነት\nልጆቿን በጸሎት ለምነህ ያስማርክላት ",
            "እጅጉን ይበልጣል ከዓለሙ ሁሉ ዜና\nገድልህን ማዳመጥ በእምነት በትሕትና\nገብረመንፈስቅዱስ የአምላክ ባለሟሉ\nስምህን በማሰብ ስለአንተ ይማራሉ",
            "ጠልፎ ከሚጥለን ሰይጣን መሰናክል\nበአንተ አማላጅነት ለማለፍ እንድንችል\nአማልደን ስንልህ ፈጥነህ ድረስልን\nከመውድቅ አድነህ በድጋፍህ አንሳን \n",
            "",
            "",
            "",
            "",
            "",
            ""
          ]
        }
      }
    },
    {
      "id": "47",
      "Timestamp": 45862.51222390046,
      "Title": "ያማልዱናል",
      "singer": "ሌላ",
      "singerOther": "ዲ/ን ዘሪሁን ወ/ትንሳኤ, ዲ/ን ሰሎሞን ወ/ትንሳኤ, ገነት ውቤ , መሰረት ውቤ",
      "about": [
        "የቅዱሳን ጻድቃንና ሰማዕታት"
      ],
      "minor_holidays": [],
      "main_holidays": [],
      "angels": [],
      "Trinity_Song": {
        "Tir": false,
        "Hamle": false,
        "Mesgana": false
      },
      "St_Mary_Song": {
        "Yekatit": false,
        "Nehase": false,
        "Mesgana": false
      },
      "K_Gebriel_Song": {
        "Tahsas": false,
        "Hamle": false,
        "Mesgana": false
      },
      "songLyrics": {
        "isShortSong": false,
        "shortLyrics": {
          "lyrics": "",
          "translation": ""
        },
        "longLyrics": {
          "chorus": "ቅዱሳን ነቢያት ወሐዋርያት\nቅዱሳን ጻድቃን ወሰማዕታት\nያማልዱናል ከአምላከ ምሕረት\nደግሞም ያሰጡናል ጸጋና በረከት",
          "verse": [
            "ቀድመው ተነበዩ -  -  - ነቢያት\nየጌታን መወለድ             \"      \"\nትንሣኤ ዕርገቱን            \"      \"   \nየዳግም መምጣቱን        \"      \"\nእኛም ተስፋ አድርገን    \"      \"\nበመጽሐፍ ያለውን         \"      \"\nስማቸውን ጠራን            \"      \"\nበረከት ለማግኘት           \"      \"",
            "እንዴት መመረጥ ነው -  -  ሐዋርያት\nከጌታ ጋር መኖር                \"      \"\nበዋለበት ውለው                  \"      \"\nበአደረበት ማደር                \"      \"\nበምድር ያሰሩት                 \"      \"\nበሰማይ ታሰረ                    \"      \"\nበምድር የፈቱት                \"      \"\nበሰማይ ነጻ ነው                 \"      \"",
            "ስለ ጌታ ፍቅር -  -  -     ሰማዕታት\nመከራን መቀበል\nበሕይወት ማስተማር\nመስቀሉን መሸከም \nለተመረጠ ነው \nለሁሉ አይቻልም \nእኛም በገድላቸው \nእንደመማለን ",
            "ትሩፋት ምግባርን -  -  - ጻድቃን\nለማድረግ የበቁ               \"      \"\nስለ ጌታ ፍቅር                \"      \"\nዓለምን የናቁ                  \"      \"\nበበረከታቸው                 \"      \"\nእኛን ያስባረኩ               \"      \"\nበረድኤታቸው               \"      \"\nበሥራ የጸደቁ                  \"      \"",
            "",
            "",
            "",
            "",
            "",
            ""
          ]
        }
      }
    },
    {
      "id": "48",
      "Timestamp": 45869.41184568287,
      "Title": "ያሬድ ካህኑ ዘመረ ",
      "singer": "ሌላ",
      "singerOther": "ብዙአየሁ ተመስገን ",
      "about": [
        "የቅዱሳን ጻድቃንና ሰማዕታት"
      ],
      "minor_holidays": [],
      "main_holidays": [],
      "angels": [],
      "Trinity_Song": {
        "Tir": false,
        "Hamle": false,
        "Mesgana": false
      },
      "St_Mary_Song": {
        "Yekatit": false,
        "Nehase": false,
        "Mesgana": false
      },
      "K_Gebriel_Song": {
        "Tahsas": false,
        "Hamle": false,
        "Mesgana": false
      },
      "songLyrics": {
        "isShortSong": false,
        "shortLyrics": {
          "lyrics": "",
          "translation": ""
        },
        "longLyrics": {
          "chorus": "ያሬድ ካህኑ ዘመረ /2/\nዘመረ ያሬድ ዘመረ\nአምላኩን አመሰገነ",
          "verse": [
            "አርያም በማለት  ያሬድ ዘመረ\nማኅሌት ጀመረ ያሬድ ዘመረ\nዜማውን ከመልእክት እያስተባበረ\nምስጋና አቀረበ ያሬድ ዘመረ\nበዜማ መሣሪያ ያሬድ ዘመረ\nጸናጽል አነሳ ከበሮ መቋሚያ",
            "በግዕዝ በዕዝል ያሬድ ዘመረ\nበአራራይ ዜማ ያሬድ ዘመረ \nከብሉይ ከሐዲስ ምሥጢር እያስማማ\nበዜማው ምልክት ያሬድ ዘመረ\nየአምላክን መከራ ያሬድ ዘመረ\nየመስቀሉን ነገር የማዳኑን ሥራ",
            "ደሙ እየፈሰሰ ያሬድ ዘመረ\nበጦር ተወግቶ ያሬድ ዘመረ\nሊቁ ማኅሌታይ በመንፈስ ተቃኝቶ\nበጥዑም ልሳኑ ያሬድ ዘመረ\nበተሰጠው ጸጋ ያሬድ ዘመረ\nለንጉሥ እግዚአብሔር ለአልፋ ዖሜጋ",
            "ድጓ ጾመድጓ  ያሬድ ዘመረ \nምዕራፍ መዋሲት ያሬድ ዘመረ\nምሥጢር ተገልጦለት በሰማይ መላእክት\nየዜማ መሠረት  ያሬድ ዘመረ\nፈልፈለ ዝማሬ  ያሬድ ዘመረ\nየኢትዮጲያ ኩራት የተዋሕዶ ፍሬ",
            "",
            "",
            "",
            "",
            "",
            ""
          ]
        }
      }
    },
    {
      "id": "49",
      "Timestamp": 45869.4237577662,
      "Title": "ያሬድ ፈልፈለ ማኅሌት ",
      "singer": "ሌላ",
      "about": [
        "የቅዱሳን ጻድቃንና ሰማዕታት"
      ],
      "minor_holidays": [],
      "main_holidays": [],
      "angels": [],
      "Trinity_Song": {
        "Tir": false,
        "Hamle": false,
        "Mesgana": false
      },
      "St_Mary_Song": {
        "Yekatit": false,
        "Nehase": false,
        "Mesgana": false
      },
      "K_Gebriel_Song": {
        "Tahsas": false,
        "Hamle": false,
        "Mesgana": false
      },
      "songLyrics": {
        "isShortSong": true,
        "shortLyrics": {
          "lyrics": "ያሬድ ፈልፈለ ማኅሌት ወቅኔያት ወባሕረ ጥበባት/2/\nእስመ ኮንከ መርሐ ለዘምሮ ለኢትዮጵያ ያሬድ ካህን ጥዑመ ልሳን/2/",
          "translation": ""
        },
        "longLyrics": {
          "chorus": "",
          "verse": [
            "",
            "",
            "",
            "",
            "",
            "",
            "",
            "",
            "",
            ""
          ]
        }
      }
    },
    {
      "id": "50",
      "Timestamp": 45869.60551334491,
      "Title": "ይቤሎ  መንፈስ ቅዱስ",
      "singer": "ሌላ",
      "about": [
        "የቅዱሳን ጻድቃንና ሰማዕታት"
      ],
      "minor_holidays": [],
      "main_holidays": [],
      "angels": [],
      "Trinity_Song": {
        "Tir": false,
        "Hamle": false,
        "Mesgana": false
      },
      "St_Mary_Song": {
        "Yekatit": false,
        "Nehase": false,
        "Mesgana": false
      },
      "K_Gebriel_Song": {
        "Tahsas": false,
        "Hamle": false,
        "Mesgana": false
      },
      "songLyrics": {
        "isShortSong": true,
        "shortLyrics": {
          "lyrics": "ይቤሎ መንፈስ ቅዱስ ለፊልጶስ ሑር ወትልዎ ለዝንቱ ሠረገላ ዘአፍራስ /2/ \nፊልጶ ስ መሀሮ ለባኮስ በእንተ ክርስቶስ ወአጥመቆ በማየ ጥምቀት ሐዲስ /2/ ",
          "translation": "አለው መንፈስ ቅዱስ ፊልጶስን ሂድና ተከተለው ይህንን የአፍራስ ሠረገላ /2/ \nፊልጶስ አስተማረ ለባኮስ ስለ ክርስቶስ አጠመቀውም በማየ ጥምቀት ሐዲስ /2/"
        },
        "longLyrics": {
          "chorus": "",
          "verse": [
            "",
            "",
            "",
            "",
            "",
            "",
            "",
            "",
            "",
            ""
          ]
        }
      }
    },
    {
      "id": "51",
      "Timestamp": 45868.66748239583,
      "Title": "ደም ወማይ ",
      "singer": "ሌላ",
      "about": [
        "የቅዱሳን ጻድቃንና ሰማዕታት"
      ],
      "minor_holidays": [],
      "main_holidays": [],
      "angels": [],
      "Trinity_Song": {
        "Tir": false,
        "Hamle": false,
        "Mesgana": false
      },
      "St_Mary_Song": {
        "Yekatit": false,
        "Nehase": false,
        "Mesgana": false
      },
      "K_Gebriel_Song": {
        "Tahsas": false,
        "Hamle": false,
        "Mesgana": false
      },
      "songLyrics": {
        "isShortSong": true,
        "shortLyrics": {
          "lyrics": "ደም ወማይ ወሐሊብ እምነ ክሳዱ/ፈልፈለ/2/\nሶበ ተከለለ /2/ ጊዮርጊስ ሶበ ተከለለ /2/ ",
          "translation": "ጊዮርጊስ አንገቱን በተቆረጠ ጊዜ ደም ውኃ እና ወተት ወጣ"
        },
        "longLyrics": {
          "chorus": "",
          "verse": [
            "",
            "",
            "",
            "",
            "",
            "",
            "",
            "",
            "",
            ""
          ]
        }
      }
    },
    {
      "id": "52",
      "Timestamp": 45869.44061524306,
      "Title": "ደምፀ ወተሰብከ",
      "singer": "ሌላ",
      "about": [
        "የቅዱሳን ጻድቃንና ሰማዕታት"
      ],
      "minor_holidays": [],
      "main_holidays": [],
      "angels": [],
      "Trinity_Song": {
        "Tir": false,
        "Hamle": false,
        "Mesgana": false
      },
      "St_Mary_Song": {
        "Yekatit": false,
        "Nehase": false,
        "Mesgana": false
      },
      "K_Gebriel_Song": {
        "Tahsas": false,
        "Hamle": false,
        "Mesgana": false
      },
      "songLyrics": {
        "isShortSong": true,
        "shortLyrics": {
          "lyrics": "ደምፀ ወተሰብከ ውስተ ዓለም ዓለም ውስተ ዓለም /2/\nለሳሙኤል ኮከብ ገዳም ትሩፍ ዜና ምግባሩ /2/",
          "translation": "የበረሃው ኮከብ እና የምግባሩ ትሩፋት ነገር የሚታወቀው ሳሙኤል በዓለም ውስጥ ተነገረ ተሰበከም፡፡"
        },
        "longLyrics": {
          "chorus": "",
          "verse": [
            "",
            "",
            "",
            "",
            "",
            "",
            "",
            "",
            "",
            ""
          ]
        }
      }
    },
    {
      "id": "53",
      "Timestamp": 45869.59759010417,
      "Title": "ገባሬ መንክራት ሰማዕት መርቆሬዎስ",
      "singer": "ማሕበረ ቅዱሳን",
      "about": [
        "የቅዱሳን ጻድቃንና ሰማዕታት"
      ],
      "minor_holidays": [],
      "main_holidays": [],
      "angels": [],
      "Trinity_Song": {
        "Tir": false,
        "Hamle": false,
        "Mesgana": false
      },
      "St_Mary_Song": {
        "Yekatit": false,
        "Nehase": false,
        "Mesgana": false
      },
      "K_Gebriel_Song": {
        "Tahsas": false,
        "Hamle": false,
        "Mesgana": false
      },
      "songLyrics": {
        "isShortSong": false,
        "shortLyrics": {
          "lyrics": "",
          "translation": ""
        },
        "longLyrics": {
          "chorus": "ገባሬ መንክራት ሰማዕት መርቆሬዎስ\nተራድአነ በገሃድ ተራድአነ /2/",
          "verse": [
            "በአረማዊ ወጣት መድኃኒት የሆንከው\nከአላዊያን ጠብቀህ ከሞት የታደግከው\nካለመኖር ወደ መኖር የመለስከው\nተራዳን በሃይማኖት ሆነን ለደከምነው /2/",
            "ዛሬም በእኛ ዘመን እንደ ኡልያኖስ\nጣዖት የሚያመልኩ የወጡ ከመንፈስ\nከእርስት እንዳይለዩን እደር በእኛ መሃል\nጥበብህ ኃይል ይሁነን መርቆሬዎስ ኃያል",
            "የሮማዊ ሰማዕት የጳጳሳት ደስታ\nየእግዚአብሔር አገልጋይ የኢትዮጵያ አለኝታ\nከእስር ቤት ወጥቶ ስዕልህ በተአምር\nኡልያኖስን ገድሎት ተመለሰ በክብር",
            "የአብ ወዳጁ የእግዚአብሔር አገልጋይ\nልመናችንን አድርስ ወደ አምላክ አዶናይ\nበሞት እንዳንጠፋ በሕይወት ጠብቀን\nበአንተ ተባርከናል ኪዳንህን አምነን",
            "",
            "",
            "",
            "",
            "",
            ""
          ]
        }
      }
    },
    {
      "id": "54",
      "Timestamp": 45869.39938037037,
      "Title": "ገባሬ መንክራት ጊዮርጊስ ",
      "singer": "ሌላ",
      "about": [
        "የቅዱሳን ጻድቃንና ሰማዕታት"
      ],
      "minor_holidays": [],
      "main_holidays": [],
      "angels": [],
      "Trinity_Song": {
        "Tir": false,
        "Hamle": false,
        "Mesgana": false
      },
      "St_Mary_Song": {
        "Yekatit": false,
        "Nehase": false,
        "Mesgana": false
      },
      "K_Gebriel_Song": {
        "Tahsas": false,
        "Hamle": false,
        "Mesgana": false
      },
      "songLyrics": {
        "isShortSong": true,
        "shortLyrics": {
          "lyrics": "ገባሬ መንክራት ጊዮርጊስ በአቊጽሎ ይቡስ ዓምድ /2/\nተራድአነ በገሃድ ተራድአነ /2/",
          "translation": "ደረቁን ምሰሶ በማለምለም ተአምር ያደረክ ፈጥነህ ዕርዳኝ"
        },
        "longLyrics": {
          "chorus": "",
          "verse": [
            "",
            "",
            "",
            "",
            "",
            "",
            "",
            "",
            "",
            ""
          ]
        }
      }
    },
    {
      "id": "55",
      "Timestamp": 45869.40763184028,
      "Title": "ገብረ መንፈስ ቅዱስ ",
      "singer": "ሌላ",
      "about": [
        "የቅዱሳን ጻድቃንና ሰማዕታት"
      ],
      "minor_holidays": [],
      "main_holidays": [],
      "angels": [],
      "Trinity_Song": {
        "Tir": false,
        "Hamle": false,
        "Mesgana": false
      },
      "St_Mary_Song": {
        "Yekatit": false,
        "Nehase": false,
        "Mesgana": false
      },
      "K_Gebriel_Song": {
        "Tahsas": false,
        "Hamle": false,
        "Mesgana": false
      },
      "songLyrics": {
        "isShortSong": true,
        "shortLyrics": {
          "lyrics": "ገብረ መንፈስ ቅዱስ የዓለም ብርሃን ናቸው /2/\nይኸው ለዘለዓለም ያበራል ሥራቸው /2/",
          "translation": ""
        },
        "longLyrics": {
          "chorus": "",
          "verse": [
            "",
            "",
            "",
            "",
            "",
            "",
            "",
            "",
            "",
            ""
          ]
        }
      }
    },
    {
      "id": "56",
      "Timestamp": 45866.597633576384,
      "Title": "ገድሉ ተአምራቱ",
      "singer": "ዘማሪት ፋንቱ ወልዴ",
      "about": [
        "የቅዱሳን ጻድቃንና ሰማዕታት"
      ],
      "minor_holidays": [],
      "main_holidays": [],
      "angels": [],
      "Trinity_Song": {
        "Tir": false,
        "Hamle": false,
        "Mesgana": false
      },
      "St_Mary_Song": {
        "Yekatit": false,
        "Nehase": false,
        "Mesgana": false
      },
      "K_Gebriel_Song": {
        "Tahsas": false,
        "Hamle": false,
        "Mesgana": false
      },
      "songLyrics": {
        "isShortSong": false,
        "shortLyrics": {
          "lyrics": "",
          "translation": ""
        },
        "longLyrics": {
          "chorus": "ገድሉ ተአምራቱ እጅግ ብዙ ነው\nጣኦትን አዋርዶ የተሸለመው \nየተዋሕዶ ኮከብ ተክለሐዋርያ\nአባ ተክለ ሃይማኖት ዘኢትዮጵያ ",
          "verse": [
            "ዳግማዊ ዮሐንስ ጠፈር የታጠቀ\nንጹሕ ባህታዊ ጠላት  ያስጨነቀ \nየጸጋ ዘአብ ፍሬ ዛፍ ሆኖ በቀለ\nበደብረ ሊባኖስ መናኝ አስከተለ ",
            "ደካማ መስሏቸው በአንድ እግሩ ቢያዩት\nባላስድስት ክንፉ ተክለአብ የእኔ አባት \nእርሱስ አንበሳ ነው ትናገር ደብረ አስቦ\nሌጌዎን ሲዋረድ እፍረት ተከናንቦ ",
            "ከካህናት መካከል ኅሩይ ነው ተክለአብ\nመጣው ከገዳምህ ልሳለለምህ ብዬ \nኢትዮጵያዊው ቅዱስ አባ ተክለሃይማኖት \nወልድ ዋሕድ ብለህ ምድሪቱን ቀደስካት",
            "የባረከው ውኃ የረገጥከው መሬት \nጥላህ ያረፈበት ሆኗል ጠበል እምነት\nኑና ተመልከቱ ድውያን ሲፈቱ\nይሰብካል ተክለአብ  ዛሬም እንደጥንቱ",
            "",
            "",
            "",
            "",
            "",
            ""
          ]
        }
      }
    },
    {
      "id": "57",
      "Timestamp": 45869.407225358795,
      "Title": "ጊዮርጊስ በዚያች ቀን",
      "singer": "ማሕበረ ቅዱሳን",
      "about": [
        "የቅዱሳን ጻድቃንና ሰማዕታት"
      ],
      "minor_holidays": [],
      "main_holidays": [],
      "angels": [],
      "Trinity_Song": {
        "Tir": false,
        "Hamle": false,
        "Mesgana": false
      },
      "St_Mary_Song": {
        "Yekatit": false,
        "Nehase": false,
        "Mesgana": false
      },
      "K_Gebriel_Song": {
        "Tahsas": false,
        "Hamle": false,
        "Mesgana": false
      },
      "songLyrics": {
        "isShortSong": false,
        "shortLyrics": {
          "lyrics": "",
          "translation": ""
        },
        "longLyrics": {
          "chorus": "ጊዮርጊስ በዚያች ቀን ከፈተናው አንጻር\nስለ ሃይማኖቱ የታየው ምን ነበር\n",
          "verse": [
            "ያመነውን አምላክ አላውቀውም እንዲል\nበሥልጣን በገንዘብ እርሱን ለመሸንገል\nየዱድያኖስ ጭፍሮች ነበር ሲያሴሩበት\nልቡናው ምን አለ ሲቀርብ ለመስዋዕት",
            "ስገድ ባሉት ጊዜ ሰው ለሠራው ምስል\nትዝ አለው ጊዮርጊስ የአምላኩ ሕያው  ቃል\nከሠለስቱ ደቂቅ ከዳንኤል ጋራ\nበእሳት ነበልባል ውስጥ ተአምር ሲሠራ",
            "ቂርቆስ ኢየሉጣን ከመቃጠል ዋጅቶ\nያቀዘቀዘውን ፍሉን ውኃ አጥፍቶ\nአስታውሷል ጊዮርጊስ ያንን ኃያል ጌታ\nመስቀል መሸከሙን በዚያች ጎልጎታ",
            "ጴጥሮስና ጳውሎስ አባቶቹን መስሎ\nሞትን አሸነፈ በእምነት ተጋድሎ\nእንድንጸና በእምነት ይቺን ዓለም ንቀን\nበሰማዕቱ ምልጃ አምላክ ይጠብቀን",
            "",
            "",
            "",
            "",
            "",
            ""
          ]
        }
      }
    },
    {
      "id": "58",
      "Timestamp": 45869.40876414352,
      "Title": "ሃሌ ሉያ ግሩማን መላእክት ",
      "singer": "ሌላ",
      "about": [
        "የቅዱሳን ጻድቃንና ሰማዕታት"
      ],
      "minor_holidays": [],
      "main_holidays": [],
      "angels": [],
      "Trinity_Song": {
        "Tir": false,
        "Hamle": false,
        "Mesgana": false
      },
      "St_Mary_Song": {
        "Yekatit": false,
        "Nehase": false,
        "Mesgana": false
      },
      "K_Gebriel_Song": {
        "Tahsas": false,
        "Hamle": false,
        "Mesgana": false
      },
      "songLyrics": {
        "isShortSong": true,
        "shortLyrics": {
          "lyrics": "ሃሌ ሉያ ግሩማን መላእክት ሱራፌል ወኪሩቤል እለ አክናፊሆሙ ነበልባል /2/\nወረዱ ዮም ይትቀበሉከ በብሂል አማን ገብረ መንፈስ ቅዱስ ገባሬ ኃይል /2/",
          "translation": "ክንፎቻቸው ነበልባል የሆኑ የሚያስፈሩ መላእክት ሱራፌልና ኪሩቤል ገብረ መንፈስ ቅዱስ በእውነት ተአምረኛ ነህ እያሉ ሊቀበሉህ ወረዱ"
        },
        "longLyrics": {
          "chorus": "",
          "verse": [
            "",
            "",
            "",
            "",
            "",
            "",
            "",
            "",
            "",
            ""
          ]
        }
      }
    },
    {
      "id": "59",
      "Timestamp": 45868.670919027776,
      "Title": "ጸለየ ቅዱስ ጊዮርጊስ ",
      "singer": "ሌላ",
      "about": [
        "የቅዱሳን ጻድቃንና ሰማዕታት"
      ],
      "minor_holidays": [],
      "main_holidays": [],
      "angels": [],
      "Trinity_Song": {
        "Tir": false,
        "Hamle": false,
        "Mesgana": false
      },
      "St_Mary_Song": {
        "Yekatit": false,
        "Nehase": false,
        "Mesgana": false
      },
      "K_Gebriel_Song": {
        "Tahsas": false,
        "Hamle": false,
        "Mesgana": false
      },
      "songLyrics": {
        "isShortSong": true,
        "shortLyrics": {
          "lyrics": "ጸለየ ቅዱስ ጊዮርጊስ እንዘ ይብል /2/\nኢትግድፋ ለነፍስየ ኢየሱስ ክርስቶስ /2/",
          "translation": "ቅዱስ ጊዮርጊስ እንዲህ ሲል ለመነ ጌታዬ ኢየሱስ ክርስቶስ ሆይ ነፍሴን አትተዋት"
        },
        "longLyrics": {
          "chorus": "",
          "verse": [
            "",
            "",
            "",
            "",
            "",
            "",
            "",
            "",
            "",
            ""
          ]
        }
      }
    },
    {
      "id": "60",
      "Timestamp": 45869.60470604167,
      "Title": "ጸለዩ ባስልዮስ ወጎርጎርዮስ",
      "singer": "ሌላ",
      "about": [
        "የቅዱሳን ጻድቃንና ሰማዕታት"
      ],
      "minor_holidays": [],
      "main_holidays": [],
      "angels": [],
      "Trinity_Song": {
        "Tir": false,
        "Hamle": false,
        "Mesgana": false
      },
      "St_Mary_Song": {
        "Yekatit": false,
        "Nehase": false,
        "Mesgana": false
      },
      "K_Gebriel_Song": {
        "Tahsas": false,
        "Hamle": false,
        "Mesgana": false
      },
      "songLyrics": {
        "isShortSong": true,
        "shortLyrics": {
          "lyrics": "ጸለዩ ባስልዮስ ወጎርጎርዮስ ኀበ ሥዕሉ ለቅዱስ መርቆሬዎስ /2/\nደነነ ሥዕል /2/ ዘመርቆሬዎስ ከመ ኦሆ ዘይብል ወተፈሥሑ ባስልዮስ ወጎርጎርዮስ /2/",
          "translation": "ጸለዩ ባስልዮስና ጎርጎርዮስ ወደ ሥዕሉ ለቅዱስ መርቆሬዎስ /2/\nዝቅ አለ ሥዕል /2/ የመርቆሬዎስ አቤት እንደሚል ተደሰቱ ባስልዮስ ጎርጎርዮስም /2/"
        },
        "longLyrics": {
          "chorus": "",
          "verse": [
            "",
            "",
            "",
            "",
            "",
            "",
            "",
            "",
            "",
            ""
          ]
        }
      }
    },
    {
      "id": "61",
      "Timestamp": 45862.50635127314,
      "Title": "ጻድቃን ሰማዕታት በሙሉ",
      "singer": "ሌላ",
      "singerOther": "ተምሮ ማስተማር ሰ/ት/ቤት ",
      "about": [
        "የቅዱሳን ጻድቃንና ሰማዕታት"
      ],
      "minor_holidays": [],
      "main_holidays": [],
      "angels": [],
      "Trinity_Song": {
        "Tir": false,
        "Hamle": false,
        "Mesgana": false
      },
      "St_Mary_Song": {
        "Yekatit": false,
        "Nehase": false,
        "Mesgana": false
      },
      "K_Gebriel_Song": {
        "Tahsas": false,
        "Hamle": false,
        "Mesgana": false
      },
      "songLyrics": {
        "isShortSong": false,
        "shortLyrics": {
          "lyrics": "",
          "translation": ""
        },
        "longLyrics": {
          "chorus": "ጻድቃን ሰማዕታት በሙሉ \nበአካለ ሥጋና/በአካለ ነፍስ/2/ያሉ\nከፈጣሪ አማልደው እኛን ያስምራሉ",
          "verse": [
            "የእግዚአብሔር ዓይኖቹ  ጻድቃንን ከማየት\nጆሮዎቹም አይርቁም እነሱን ከመስማት\nየጻድቅ ሰው ጸሎት ኃይልን ታደርጋለች\nበምልጃቸው አምነን አናመንታ በአንዳች",
            "ጊዜአዊው መከራ ሳያሳቅቃቸው\nእሳትና ስለት ሳያስፈራራቸው\nሰማያዊ ተስፋ ስለሚታያቸው\nበመከራ ሁሉ ጸኑ በእምነታቸው",
            "ኃጥኡ ነዌ እንኳን በሲዖል እያለ\nስለወንድሞቹ  ምሕረት ከለመነ\nእናንተማ ጻድቃን በገነት ያላችሁ\nምነኛ ትረዱን አምነን ስንጠራችሁ",
            "ቀዝቃዛ  ውኃ እንኳን በጻድቅ ሰው ስም\nየሚያጠጣ ቢኖር ዋጋው  አይጠፋም\nብሎ እንዳስተማረን ጌታ  በወንጌል\nአምነን እንፈፅመው ዋጋ ይሰጠናል",
            "",
            "",
            "",
            "",
            "",
            ""
          ]
        }
      }
    },
    {
      "id": "62",
      "Timestamp": 45866.59028971065,
      "Title": "ጻድቃን ኢሞቱ",
      "singer": "ሌላ",
      "about": [
        "የቅዱሳን ጻድቃንና ሰማዕታት"
      ],
      "minor_holidays": [],
      "main_holidays": [],
      "angels": [],
      "Trinity_Song": {
        "Tir": false,
        "Hamle": false,
        "Mesgana": false
      },
      "St_Mary_Song": {
        "Yekatit": false,
        "Nehase": false,
        "Mesgana": false
      },
      "K_Gebriel_Song": {
        "Tahsas": false,
        "Hamle": false,
        "Mesgana": false
      },
      "songLyrics": {
        "isShortSong": true,
        "shortLyrics": {
          "lyrics": "ጻድቃንሰ ኢሞቱ ኀበ እግዚኦሙ/ነገዱ/2/\nበመንግሥተ ሰማይ /4/ ይሁቦሙ ዘፈቀዱ",
          "translation": "ጻድቃን አልሞቱም ነገር ግን ወደ ጌታቸው ሄዱ እርሱም በሰማያዊ ቤቱ የወደዱትን ሰጣቸው፡፡"
        },
        "longLyrics": {
          "chorus": "",
          "verse": [
            "",
            "",
            "",
            "",
            "",
            "",
            "",
            "",
            "",
            ""
          ]
        }
      }
    },
    {
      "id": "63",
      "Timestamp": 45869.41048177083,
      "Title": "ጼና አልባሲሁ ",
      "singer": "ሌላ",
      "about": [
        "የቅዱሳን ጻድቃንና ሰማዕታት"
      ],
      "minor_holidays": [],
      "main_holidays": [],
      "angels": [],
      "Trinity_Song": {
        "Tir": false,
        "Hamle": false,
        "Mesgana": false
      },
      "St_Mary_Song": {
        "Yekatit": false,
        "Nehase": false,
        "Mesgana": false
      },
      "K_Gebriel_Song": {
        "Tahsas": false,
        "Hamle": false,
        "Mesgana": false
      },
      "songLyrics": {
        "isShortSong": true,
        "shortLyrics": {
          "lyrics": "ጼና አልባሲሁ /2/ ለገብረ መንፈስ ቅዱስ ከመ ጼና ስኂን /2/\nአልባሲሁ ዘሜላት /2/ ዘወረደ ውስተ ገነት /2/",
          "translation": "የገብረ መንፈስ ቅዱስ ልብሳቸው እንደ ሽቱ ያማረ ነው ደግሞም ልብሳቸው እንደ ነጭ ሐር ነው እሱም ወደ ገነት የወረደ ነው"
        },
        "longLyrics": {
          "chorus": "",
          "verse": [
            "",
            "",
            "",
            "",
            "",
            "",
            "",
            "",
            "",
            ""
          ]
        }
      }
    },
    {
      "id": "64",
      "Timestamp": 45869.4508789699,
      "Title": "ጽኑ ሰማዕት",
      "singer": "ሌላ",
      "about": [
        "የቅዱሳን ጻድቃንና ሰማዕታት"
      ],
      "minor_holidays": [],
      "main_holidays": [],
      "angels": [],
      "Trinity_Song": {
        "Tir": false,
        "Hamle": false,
        "Mesgana": false
      },
      "St_Mary_Song": {
        "Yekatit": false,
        "Nehase": false,
        "Mesgana": false
      },
      "K_Gebriel_Song": {
        "Tahsas": false,
        "Hamle": false,
        "Mesgana": false
      },
      "songLyrics": {
        "isShortSong": false,
        "shortLyrics": {
          "lyrics": "",
          "translation": ""
        },
        "longLyrics": {
          "chorus": "ጽኑ ሰማዕት የእምነት አርበኛ\nአርሴማ ነይ ነይ ወደኛ",
          "verse": [
            "ነይ ነይ ቅዱስ አትናትዮስ\n›› ›› በሥዕለት ያገኙሽ\n›› ›› ብሉይን ከሀዲስ\n›› ›› ጠንቅቀሽ የተማርሽ\n›› ›› በፍፁም ትሕትና\n›› ›› በጸሎት የተጋሽ\n›› ›› አርሴማ ልዩ ነሽ\n›› ›› አምላክ የመረጠሸ",
            "ነይ ነይ ውበትም ሀሰት ነው\n›› ›› ደም ግባትም ከንቱ\n›› ›› ንብረት ትዳር ሁሉ\n›› ›› አላፊ ውዕቱ\n›› ›› ንግሥት መባልን\n›› ›› በፍጹም ሳትሻ\n›› ›› ዓለምን በመናቅ\n›› ›› ገባች ወደዋሻ",
            "ነይ ነይ አረመኔው ድርጣድስ\n›› ››  ቢያሰቃይሽም\n›› ››  ውበቴ ክርስቶስ\n›› ››  ነው ብለሽ ሰበክሽ\n›› ››  አንገትሽን ለሰይፍ\n›› ››  አሳልፈሽ ሰጠሸ\n›› ››  ክብርሽም ተገልጾ\n›› ››  ለዓለም አበራሽ",
            "ነይ ነይ አርአያ ልትሆኝን\n›› ››  ለእኛ ለሁላችን\n›› ››  ፈፅመሽ አሳየሽ\n›› ››  ታላቅ ተጋድሎሽን\n›› ››  ይህን ዓለም ድል መንሳት\n›› ››  አቅቶናል እና\n›› ››  አርሴማ አትለይን\n›› ››  በእምነት እንድንጸና\n",
            "",
            "",
            "",
            "",
            "",
            ""
          ]
        }
      }
    },
    {
      "id": "65",
      "Timestamp": 45868.66960666666,
      "Title": "ፀሐይ ዘልዳ ",
      "singer": "ሌላ",
      "singerOther": "ደብረ ብርሃን ሰ/ት/ቤት ",
      "about": [
        "የቅዱሳን ጻድቃንና ሰማዕታት"
      ],
      "minor_holidays": [],
      "main_holidays": [],
      "angels": [],
      "Trinity_Song": {
        "Tir": false,
        "Hamle": false,
        "Mesgana": false
      },
      "St_Mary_Song": {
        "Yekatit": false,
        "Nehase": false,
        "Mesgana": false
      },
      "K_Gebriel_Song": {
        "Tahsas": false,
        "Hamle": false,
        "Mesgana": false
      },
      "songLyrics": {
        "isShortSong": false,
        "shortLyrics": {
          "lyrics": "",
          "translation": ""
        },
        "longLyrics": {
          "chorus": "እምነ ሠናያት ኩሎ እለ ውስተ ባሕር ወየብስ /2/\nሶበ ነጸርኩ በሃሢሥ ዘከማከ አልቦ ጊዮርጊስ /2/",
          "verse": [
            "የመከራ ገፈት ቀምሳ ለሰጠችህ\nልጅ ሆነሃልና ለማርያም እናትህ\nስምዐ ክርስቶስ አርአያ ሰማዕታት\nሆነህ የተሰየምክ የሰማዕታት አባት",
            "የገድልህን ነገር ጆሯችን ሲሰማ\nልባችን ይቀልጣል ለጽናትህ ዜና\nየጌታህን ትእግሥት ቀራንዮን እያሰብክ\nበወጣትነትህ ተጋድሎህን ፈጸምክ",
            "በጭንቅ በመከራ ጽናትህ ሲፈተን\nከአምላክ ተምረህ ቁጣን ሳትናገር\nሁሉን ስለ ጌታ ችለህ ታግሠሃል\nየብርሃን አክሊልን በሰማይ ደፍተሃል",
            "ሥዕለ ገጽህን ዘወትር እያየን\nነገረ ገድልህን ሁልጊዜ እያደነቅን\nፍቅርህ በልባችን ስለተሣለብን\nይኸው አንዘምራለን ጊዮርጊስ እያልን",
            "",
            "",
            "",
            "",
            "",
            ""
          ]
        }
      }
    },
    {
      "id": "66",
      "Timestamp": 45869.40500775463,
      "Title": "ፍጡነ ረድኤት",
      "singer": "ሌላ",
      "about": [
        "የቅዱሳን ጻድቃንና ሰማዕታት"
      ],
      "minor_holidays": [],
      "main_holidays": [],
      "angels": [],
      "Trinity_Song": {
        "Tir": false,
        "Hamle": false,
        "Mesgana": false
      },
      "St_Mary_Song": {
        "Yekatit": false,
        "Nehase": false,
        "Mesgana": false
      },
      "K_Gebriel_Song": {
        "Tahsas": false,
        "Hamle": false,
        "Mesgana": false
      },
      "songLyrics": {
        "isShortSong": true,
        "shortLyrics": {
          "lyrics": "ፍጡነ ረድኤት ጊዮርጊስ ተራድአኒ ሶበ ለገብርከ /ለዓመትከ/ ኀዘን አኀዘኒ\nወጸሎትየ /3/ ፍጡነ ስምዓኒ /2/",
          "translation": ""
        },
        "longLyrics": {
          "chorus": "",
          "verse": [
            "",
            "",
            "",
            "",
            "",
            "",
            "",
            "",
            "",
            ""
          ]
        }
      }
    }
  ]
}